[
  {
    "_metadata": {
      "extracted_at": "2025-12-02T05:52:14.800663",
      "file_path": "data/bronze/commits_2025-2-Mural-UnB.json",
      "record_count": 446
    }
  },
  {
    "sha": "e2adff3c5207bdb2eb7dfe9798b1534bb5ca72c7",
    "html_url": "https://github.com/unb-mds/2025-2-Mural-UnB/commit/e2adff3c5207bdb2eb7dfe9798b1534bb5ca72c7",
    "commit": {
      "author": {
        "name": "Tiago Bittencourt",
        "email": "tiago.bittencourt.2005@gmail.com",
        "date": "2025-12-01T23:53:33-03:00",
        "login": "TiagoSBittencourt"
      },
      "committer": {
        "name": "Tiago Bittencourt",
        "email": "tiago.bittencourt.2005@gmail.com",
        "date": "2025-12-02T02:53:33Z",
        "login": "TiagoSBittencourt"
      },
      "message": "fix(headers-cas): imagem corrijida referente ao cas da unb"
    },
    "additions": 0,
    "deletions": 0,
    "total_changes": 0,
    "repo_name": "2025-2-Mural-UnB"
  },
  {
    "sha": "cb3750c455527c125348302d05f14543de782a5d",
    "html_url": "https://github.com/unb-mds/2025-2-Mural-UnB/commit/cb3750c455527c125348302d05f14543de782a5d",
    "commit": {
      "author": {
        "name": "Tiago Bittencourt",
        "email": "tiago.bittencourt.2005@gmail.com",
        "date": "2025-12-01T23:40:05-03:00",
        "login": "TiagoSBittencourt"
      },
      "committer": {
        "name": "GitHub",
        "email": "noreply@github.com",
        "date": "2025-12-02T02:40:05Z",
        "login": null
      },
      "message": "Merge pull request #144 from unb-mds/feat/images-headers"
    },
    "additions": 23,
    "deletions": 2,
    "total_changes": 25,
    "repo_name": "2025-2-Mural-UnB"
  },
  {
    "sha": "8ee11dda3fff2ad2237e650b13afdb8fffc795f5",
    "html_url": "https://github.com/unb-mds/2025-2-Mural-UnB/commit/8ee11dda3fff2ad2237e650b13afdb8fffc795f5",
    "commit": {
      "author": {
        "name": "Tiago Bittencourt",
        "email": "tiago.bittencourt.2005@gmail.com",
        "date": "2025-12-01T23:37:07-03:00",
        "login": "TiagoSBittencourt"
      },
      "committer": {
        "name": "Tiago Bittencourt",
        "email": "tiago.bittencourt.2005@gmail.com",
        "date": "2025-12-02T02:37:07Z",
        "login": "TiagoSBittencourt"
      },
      "message": "feat(headers): adicionado headers faltantes e aprimorando existentes"
    },
    "additions": 23,
    "deletions": 2,
    "total_changes": 25,
    "repo_name": "2025-2-Mural-UnB"
  },
  {
    "sha": "e03060618959fdf2c11cf0c83dbb7546f632a286",
    "html_url": "https://github.com/unb-mds/2025-2-Mural-UnB/commit/e03060618959fdf2c11cf0c83dbb7546f632a286",
    "commit": {
      "author": {
        "name": "Matheus Saraiva Camargo",
        "email": "128329654+apptrx@users.noreply.github.com",
        "date": "2025-12-01T22:11:54-03:00",
        "login": "apptrx"
      },
      "committer": {
        "name": "GitHub",
        "email": "noreply@github.com",
        "date": "2025-12-02T01:11:54Z",
        "login": null
      },
      "message": "Merge pull request #143 from unb-mds/fix/aumentar-cobertura-testes"
    },
    "additions": 1413,
    "deletions": 1805,
    "total_changes": 3218,
    "repo_name": "2025-2-Mural-UnB"
  },
  {
    "sha": "fd9eced27f720b320a99fd7d40fcbbf48f1d5d2a",
    "html_url": "https://github.com/unb-mds/2025-2-Mural-UnB/commit/fd9eced27f720b320a99fd7d40fcbbf48f1d5d2a",
    "commit": {
      "author": {
        "name": "apptrx",
        "email": "matheusscamargo13@gmail.com",
        "date": "2025-12-01T22:05:45-03:00",
        "login": "apptrx"
      },
      "committer": {
        "name": "apptrx",
        "email": "matheusscamargo13@gmail.com",
        "date": "2025-12-02T01:05:45Z",
        "login": "apptrx"
      },
      "message": "fix(extrair-labs): corrige erro de sigla no parser de labs e estabili…"
    },
    "additions": 185,
    "deletions": 120,
    "total_changes": 305,
    "repo_name": "2025-2-Mural-UnB"
  },
  {
    "sha": "af015f477a2bb6de333d50a0860fd05ef496b939",
    "html_url": "https://github.com/unb-mds/2025-2-Mural-UnB/commit/af015f477a2bb6de333d50a0860fd05ef496b939",
    "commit": {
      "author": {
        "name": "apptrx",
        "email": "matheusscamargo13@gmail.com",
        "date": "2025-12-01T21:55:08-03:00",
        "login": "apptrx"
      },
      "committer": {
        "name": "apptrx",
        "email": "matheusscamargo13@gmail.com",
        "date": "2025-12-02T00:55:08Z",
        "login": "apptrx"
      },
      "message": "test: maximiza cobertura do script de download de PDF de labs (#143)"
    },
    "additions": 97,
    "deletions": 92,
    "total_changes": 189,
    "repo_name": "2025-2-Mural-UnB"
  },
  {
    "sha": "767d30bde5a5b2184bccb6231b3112bae3a7d98b",
    "html_url": "https://github.com/unb-mds/2025-2-Mural-UnB/commit/767d30bde5a5b2184bccb6231b3112bae3a7d98b",
    "commit": {
      "author": {
        "name": "apptrx",
        "email": "matheusscamargo13@gmail.com",
        "date": "2025-12-01T21:52:32-03:00",
        "login": "apptrx"
      },
      "committer": {
        "name": "apptrx",
        "email": "matheusscamargo13@gmail.com",
        "date": "2025-12-02T00:52:32Z",
        "login": "apptrx"
      },
      "message": "test: implementa 100% de cobertura no crawler de PDF de EJs (#143)"
    },
    "additions": 76,
    "deletions": 325,
    "total_changes": 401,
    "repo_name": "2025-2-Mural-UnB"
  },
  {
    "sha": "3a998ea37e87970b1a5f694735473d4900bb00ea",
    "html_url": "https://github.com/unb-mds/2025-2-Mural-UnB/commit/3a998ea37e87970b1a5f694735473d4900bb00ea",
    "commit": {
      "author": {
        "name": "apptrx",
        "email": "matheusscamargo13@gmail.com",
        "date": "2025-12-01T21:32:35-03:00",
        "login": "apptrx"
      },
      "committer": {
        "name": "apptrx",
        "email": "matheusscamargo13@gmail.com",
        "date": "2025-12-02T00:32:35Z",
        "login": "apptrx"
      },
      "message": "test: finaliza cobertura do processador de PDF de EJs (#143)"
    },
    "additions": 182,
    "deletions": 414,
    "total_changes": 596,
    "repo_name": "2025-2-Mural-UnB"
  },
  {
    "sha": "ef105cb198eef35f6de36e5af8a910513f62fa68",
    "html_url": "https://github.com/unb-mds/2025-2-Mural-UnB/commit/ef105cb198eef35f6de36e5af8a910513f62fa68",
    "commit": {
      "author": {
        "name": "apptrx",
        "email": "matheusscamargo13@gmail.com",
        "date": "2025-12-01T21:20:33-03:00",
        "login": "apptrx"
      },
      "committer": {
        "name": "apptrx",
        "email": "matheusscamargo13@gmail.com",
        "date": "2025-12-02T00:20:33Z",
        "login": "apptrx"
      },
      "message": "test: aumenta cobertura de embeddings e EJs (#143)"
    },
    "additions": 173,
    "deletions": 278,
    "total_changes": 451,
    "repo_name": "2025-2-Mural-UnB"
  },
  {
    "sha": "c7ad5bc0dbd01f3999974a4fb7a406cd70167631",
    "html_url": "https://github.com/unb-mds/2025-2-Mural-UnB/commit/c7ad5bc0dbd01f3999974a4fb7a406cd70167631",
    "commit": {
      "author": {
        "name": "apptrx",
        "email": "matheusscamargo13@gmail.com",
        "date": "2025-12-01T21:11:21-03:00",
        "login": "apptrx"
      },
      "committer": {
        "name": "apptrx",
        "email": "matheusscamargo13@gmail.com",
        "date": "2025-12-02T00:11:21Z",
        "login": "apptrx"
      },
      "message": "test: implementa cobertura total para gerador de embeddings Gemini (#…"
    },
    "additions": 239,
    "deletions": 352,
    "total_changes": 591,
    "repo_name": "2025-2-Mural-UnB"
  },
  {
    "sha": "1702ddabc6c3829a8a68dd7ce607ee0cf8628f50",
    "html_url": "https://github.com/unb-mds/2025-2-Mural-UnB/commit/1702ddabc6c3829a8a68dd7ce607ee0cf8628f50",
    "commit": {
      "author": {
        "name": "apptrx",
        "email": "matheusscamargo13@gmail.com",
        "date": "2025-12-01T21:05:33-03:00",
        "login": "apptrx"
      },
      "committer": {
        "name": "apptrx",
        "email": "matheusscamargo13@gmail.com",
        "date": "2025-12-02T00:05:33Z",
        "login": "apptrx"
      },
      "message": "test: adiciona testes unitários para alocar_tags_embeddings (#143)"
    },
    "additions": 148,
    "deletions": 74,
    "total_changes": 222,
    "repo_name": "2025-2-Mural-UnB"
  },
  {
    "sha": "5d6bac79590092ee82966e1536a5ec34afed6db7",
    "html_url": "https://github.com/unb-mds/2025-2-Mural-UnB/commit/5d6bac79590092ee82966e1536a5ec34afed6db7",
    "commit": {
      "author": {
        "name": "apptrx",
        "email": "matheusscamargo13@gmail.com",
        "date": "2025-12-01T20:58:49-03:00",
        "login": "apptrx"
      },
      "committer": {
        "name": "apptrx",
        "email": "matheusscamargo13@gmail.com",
        "date": "2025-12-01T23:58:49Z",
        "login": "apptrx"
      },
      "message": "test: adiciona testes de integração e borda para alocar_tags_ejs (#143)"
    },
    "additions": 78,
    "deletions": 68,
    "total_changes": 146,
    "repo_name": "2025-2-Mural-UnB"
  },
  {
    "sha": "a82586e75d78a32ec81b76acb4e85aaa2d231a2d",
    "html_url": "https://github.com/unb-mds/2025-2-Mural-UnB/commit/a82586e75d78a32ec81b76acb4e85aaa2d231a2d",
    "commit": {
      "author": {
        "name": "apptrx",
        "email": "matheusscamargo13@gmail.com",
        "date": "2025-12-01T20:50:28-03:00",
        "login": "apptrx"
      },
      "committer": {
        "name": "apptrx",
        "email": "matheusscamargo13@gmail.com",
        "date": "2025-12-01T23:50:28Z",
        "login": "apptrx"
      },
      "message": "test: aprimora cobertura de testes e corrige imports (#143)"
    },
    "additions": 244,
    "deletions": 139,
    "total_changes": 383,
    "repo_name": "2025-2-Mural-UnB"
  },
  {
    "sha": "36cad6fd344d9964d71caacf4a333d4327cdd9e8",
    "html_url": "https://github.com/unb-mds/2025-2-Mural-UnB/commit/36cad6fd344d9964d71caacf4a333d4327cdd9e8",
    "commit": {
      "author": {
        "name": "apptrx",
        "email": "matheusscamargo13@gmail.com",
        "date": "2025-12-01T20:27:35-03:00",
        "login": "apptrx"
      },
      "committer": {
        "name": "apptrx",
        "email": "matheusscamargo13@gmail.com",
        "date": "2025-12-01T23:27:35Z",
        "login": "apptrx"
      },
      "message": "test: aumenta cobertura dos embeddings e remove código morto (#143)"
    },
    "additions": 137,
    "deletions": 30,
    "total_changes": 167,
    "repo_name": "2025-2-Mural-UnB"
  },
  {
    "sha": "8a3baeb7f9d91c83f6cc4a17af343dbf5d252ff7",
    "html_url": "https://github.com/unb-mds/2025-2-Mural-UnB/commit/8a3baeb7f9d91c83f6cc4a17af343dbf5d252ff7",
    "commit": {
      "author": {
        "name": "apptrx",
        "email": "matheusscamargo13@gmail.com",
        "date": "2025-12-01T19:43:13-03:00",
        "login": "apptrx"
      },
      "committer": {
        "name": "apptrx",
        "email": "matheusscamargo13@gmail.com",
        "date": "2025-12-01T22:43:13Z",
        "login": "apptrx"
      },
      "message": "test: Adiciona testes de sucesso e falha (404) para labs_pdf (#103)"
    },
    "additions": 36,
    "deletions": 42,
    "total_changes": 78,
    "repo_name": "2025-2-Mural-UnB"
  },
  {
    "sha": "003d7c412d1c95d17b5652dbcb1deaedd5e5e34d",
    "html_url": "https://github.com/unb-mds/2025-2-Mural-UnB/commit/003d7c412d1c95d17b5652dbcb1deaedd5e5e34d",
    "commit": {
      "author": {
        "name": "apptrx",
        "email": "matheusscamargo13@gmail.com",
        "date": "2025-12-01T19:18:25-03:00",
        "login": "apptrx"
      },
      "committer": {
        "name": "apptrx",
        "email": "matheusscamargo13@gmail.com",
        "date": "2025-12-01T22:18:25Z",
        "login": "apptrx"
      },
      "message": "test: Refatora juntar_oportunidades e adiciona testes unitários (#103)"
    },
    "additions": 58,
    "deletions": 111,
    "total_changes": 169,
    "repo_name": "2025-2-Mural-UnB"
  },
  {
    "sha": "d613af0342d4745142627eab92023e80ac9f60d9",
    "html_url": "https://github.com/unb-mds/2025-2-Mural-UnB/commit/d613af0342d4745142627eab92023e80ac9f60d9",
    "commit": {
      "author": {
        "name": "Luan Ludry",
        "email": "lovedeskigames@gmail.com",
        "date": "2025-12-01T13:30:54-03:00",
        "login": "luanludry"
      },
      "committer": {
        "name": "GitHub",
        "email": "noreply@github.com",
        "date": "2025-12-01T16:30:54Z",
        "login": null
      },
      "message": "Update DetailPage.tsx"
    },
    "additions": 2,
    "deletions": 2,
    "total_changes": 4,
    "repo_name": "2025-2-Mural-UnB"
  },
  {
    "sha": "3dd6042b6614dbf9825aba03f32d1c9655530683",
    "html_url": "https://github.com/unb-mds/2025-2-Mural-UnB/commit/3dd6042b6614dbf9825aba03f32d1c9655530683",
    "commit": {
      "author": {
        "name": "Luan Ludry",
        "email": "lovedeskigames@gmail.com",
        "date": "2025-12-01T12:54:03-03:00",
        "login": "luanludry"
      },
      "committer": {
        "name": "GitHub",
        "email": "noreply@github.com",
        "date": "2025-12-01T15:54:03Z",
        "login": null
      },
      "message": "Merge pull request #141 from unb-mds/headers"
    },
    "additions": 159,
    "deletions": 8,
    "total_changes": 167,
    "repo_name": "2025-2-Mural-UnB"
  },
  {
    "sha": "e26ab45023bcd12abf40b5ed05710dca9e4a9f31",
    "html_url": "https://github.com/unb-mds/2025-2-Mural-UnB/commit/e26ab45023bcd12abf40b5ed05710dca9e4a9f31",
    "commit": {
      "author": {
        "name": "Luan Ludry",
        "email": "lovedeskigames@gmail.com",
        "date": "2025-12-01T11:47:51-03:00",
        "login": "luanludry"
      },
      "committer": {
        "name": "Luan Ludry",
        "email": "lovedeskigames@gmail.com",
        "date": "2025-12-01T14:47:51Z",
        "login": "luanludry"
      },
      "message": "refactor: remove unnecessary getCompanyPriority function"
    },
    "additions": 0,
    "deletions": 18,
    "total_changes": 18,
    "repo_name": "2025-2-Mural-UnB"
  },
  {
    "sha": "e6ab826cb5d6ee5829fb611c16ffceb2f04bade5",
    "html_url": "https://github.com/unb-mds/2025-2-Mural-UnB/commit/e6ab826cb5d6ee5829fb611c16ffceb2f04bade5",
    "commit": {
      "author": {
        "name": "Luan Ludry",
        "email": "lovedeskigames@gmail.com",
        "date": "2025-12-01T10:49:35-03:00",
        "login": "luanludry"
      },
      "committer": {
        "name": "Luan Ludry",
        "email": "lovedeskigames@gmail.com",
        "date": "2025-12-01T13:49:35Z",
        "login": "luanludry"
      },
      "message": "fix: add social links for UnBall team"
    },
    "additions": 26,
    "deletions": 7,
    "total_changes": 33,
    "repo_name": "2025-2-Mural-UnB"
  },
  {
    "sha": "5aaef8db5861d3ecb6b2308905935d72e0713763",
    "html_url": "https://github.com/unb-mds/2025-2-Mural-UnB/commit/5aaef8db5861d3ecb6b2308905935d72e0713763",
    "commit": {
      "author": {
        "name": "Luan Ludry",
        "email": "lovedeskigames@gmail.com",
        "date": "2025-12-01T10:44:04-03:00",
        "login": "luanludry"
      },
      "committer": {
        "name": "Luan Ludry",
        "email": "lovedeskigames@gmail.com",
        "date": "2025-12-01T13:44:04Z",
        "login": "luanludry"
      },
      "message": "fix: social equipe de competicao"
    },
    "additions": 4,
    "deletions": 16,
    "total_changes": 20,
    "repo_name": "2025-2-Mural-UnB"
  },
  {
    "sha": "831a688dcac81166059d660321626994f6370ec6",
    "html_url": "https://github.com/unb-mds/2025-2-Mural-UnB/commit/831a688dcac81166059d660321626994f6370ec6",
    "commit": {
      "author": {
        "name": "Luan Ludry",
        "email": "lovedeskigames@gmail.com",
        "date": "2025-12-01T10:37:09-03:00",
        "login": "luanludry"
      },
      "committer": {
        "name": "Luan Ludry",
        "email": "lovedeskigames@gmail.com",
        "date": "2025-12-01T13:37:09Z",
        "login": "luanludry"
      },
      "message": "feat: add support for all new header images"
    },
    "additions": 34,
    "deletions": 17,
    "total_changes": 51,
    "repo_name": "2025-2-Mural-UnB"
  },
  {
    "sha": "04655eb0128e7cfbea65669e56a9b9c5ef254ebe",
    "html_url": "https://github.com/unb-mds/2025-2-Mural-UnB/commit/04655eb0128e7cfbea65669e56a9b9c5ef254ebe",
    "commit": {
      "author": {
        "name": "Luan Ludry",
        "email": "lovedeskigames@gmail.com",
        "date": "2025-12-01T10:36:32-03:00",
        "login": "luanludry"
      },
      "committer": {
        "name": "Luan Ludry",
        "email": "lovedeskigames@gmail.com",
        "date": "2025-12-01T13:36:32Z",
        "login": "luanludry"
      },
      "message": "feat: add header images for additional teams and companies"
    },
    "additions": 0,
    "deletions": 0,
    "total_changes": 0,
    "repo_name": "2025-2-Mural-UnB"
  },
  {
    "sha": "7e6e8d7ed3e7a9449e6f99ce91154e2b4d3306df",
    "html_url": "https://github.com/unb-mds/2025-2-Mural-UnB/commit/7e6e8d7ed3e7a9449e6f99ce91154e2b4d3306df",
    "commit": {
      "author": {
        "name": "Luan Ludry",
        "email": "lovedeskigames@gmail.com",
        "date": "2025-12-01T09:37:28-03:00",
        "login": "luanludry"
      },
      "committer": {
        "name": "Luan Ludry",
        "email": "lovedeskigames@gmail.com",
        "date": "2025-12-01T12:37:28Z",
        "login": "luanludry"
      },
      "message": "feat: add header images directory for company banners"
    },
    "additions": 0,
    "deletions": 0,
    "total_changes": 0,
    "repo_name": "2025-2-Mural-UnB"
  },
  {
    "sha": "ae4235e46ee58ff19e78c2256d4c197a55de0790",
    "html_url": "https://github.com/unb-mds/2025-2-Mural-UnB/commit/ae4235e46ee58ff19e78c2256d4c197a55de0790",
    "commit": {
      "author": {
        "name": "Luan Ludry",
        "email": "lovedeskigames@gmail.com",
        "date": "2025-12-01T09:37:23-03:00",
        "login": "luanludry"
      },
      "committer": {
        "name": "Luan Ludry",
        "email": "lovedeskigames@gmail.com",
        "date": "2025-12-01T12:37:23Z",
        "login": "luanludry"
      },
      "message": "feat: add header banner to opportunity detail pages"
    },
    "additions": 128,
    "deletions": 1,
    "total_changes": 129,
    "repo_name": "2025-2-Mural-UnB"
  },
  {
    "sha": "e0845225ac7892aaae4c645e0f977c3c61070f32",
    "html_url": "https://github.com/unb-mds/2025-2-Mural-UnB/commit/e0845225ac7892aaae4c645e0f977c3c61070f32",
    "commit": {
      "author": {
        "name": "Luan Ludry",
        "email": "lovedeskigames@gmail.com",
        "date": "2025-12-01T09:37:14-03:00",
        "login": "luanludry"
      },
      "committer": {
        "name": "Luan Ludry",
        "email": "lovedeskigames@gmail.com",
        "date": "2025-12-01T12:37:14Z",
        "login": "luanludry"
      },
      "message": "feat: add company priority ordering for EJs"
    },
    "additions": 18,
    "deletions": 0,
    "total_changes": 18,
    "repo_name": "2025-2-Mural-UnB"
  },
  {
    "sha": "58f9d405088990539e61d6372398a0ca3f9cfaef",
    "html_url": "https://github.com/unb-mds/2025-2-Mural-UnB/commit/58f9d405088990539e61d6372398a0ca3f9cfaef",
    "commit": {
      "author": {
        "name": "Lucasft16",
        "email": "lucaasft16@gmail.com",
        "date": "2025-12-01T04:37:06Z",
        "login": "Lucasft16"
      },
      "committer": {
        "name": "Lucasft16",
        "email": "lucaasft16@gmail.com",
        "date": "2025-12-01T04:37:06Z",
        "login": "Lucasft16"
      },
      "message": "chore: atualizar lista de laboratórios FGA [skip ci]"
    },
    "additions": 35,
    "deletions": 35,
    "total_changes": 70,
    "repo_name": "2025-2-Mural-UnB"
  },
  {
    "sha": "effb28858a2c3a26d0a022a9f0237ceef19a1b68",
    "html_url": "https://github.com/unb-mds/2025-2-Mural-UnB/commit/effb28858a2c3a26d0a022a9f0237ceef19a1b68",
    "commit": {
      "author": {
        "name": "LucasFT",
        "email": "lucaasft16@gmail.com",
        "date": "2025-11-30T17:45:11-03:00",
        "login": "Lucasft16"
      },
      "committer": {
        "name": "LucasFT",
        "email": "lucaasft16@gmail.com",
        "date": "2025-11-30T20:45:11Z",
        "login": "Lucasft16"
      },
      "message": "fix: adiçao do gmail"
    },
    "additions": 45,
    "deletions": 63,
    "total_changes": 108,
    "repo_name": "2025-2-Mural-UnB"
  },
  {
    "sha": "c11e228fb87cf3134c3e20a539c79cd69b7c6517",
    "html_url": "https://github.com/unb-mds/2025-2-Mural-UnB/commit/c11e228fb87cf3134c3e20a539c79cd69b7c6517",
    "commit": {
      "author": {
        "name": "LucasFT",
        "email": "lucaasft16@gmail.com",
        "date": "2025-11-30T17:27:42-03:00",
        "login": "Lucasft16"
      },
      "committer": {
        "name": "LucasFT",
        "email": "lucaasft16@gmail.com",
        "date": "2025-11-30T20:27:42Z",
        "login": "Lucasft16"
      },
      "message": "fix: fix do url final e hrefs #138"
    },
    "additions": 12,
    "deletions": 12,
    "total_changes": 24,
    "repo_name": "2025-2-Mural-UnB"
  },
  {
    "sha": "376599b650854f066bd54c18b22118b3ea329e20",
    "html_url": "https://github.com/unb-mds/2025-2-Mural-UnB/commit/376599b650854f066bd54c18b22118b3ea329e20",
    "commit": {
      "author": {
        "name": "LucasFT",
        "email": "lucaasft16@gmail.com",
        "date": "2025-11-30T17:19:00-03:00",
        "login": "Lucasft16"
      },
      "committer": {
        "name": "LucasFT",
        "email": "lucaasft16@gmail.com",
        "date": "2025-11-30T20:19:00Z",
        "login": "Lucasft16"
      },
      "message": "fix: fix no css das paginas das oportunidades"
    },
    "additions": 31,
    "deletions": 20,
    "total_changes": 51,
    "repo_name": "2025-2-Mural-UnB"
  },
  {
    "sha": "9ed6e110b16f60e538399f524df03937553223d3",
    "html_url": "https://github.com/unb-mds/2025-2-Mural-UnB/commit/9ed6e110b16f60e538399f524df03937553223d3",
    "commit": {
      "author": {
        "name": "LucasFT",
        "email": "lucaasft16@gmail.com",
        "date": "2025-11-30T17:08:27-03:00",
        "login": "Lucasft16"
      },
      "committer": {
        "name": "LucasFT",
        "email": "lucaasft16@gmail.com",
        "date": "2025-11-30T20:08:27Z",
        "login": "Lucasft16"
      },
      "message": "fix: fix nas imagens das equipes de competições"
    },
    "additions": 21,
    "deletions": 17,
    "total_changes": 38,
    "repo_name": "2025-2-Mural-UnB"
  },
  {
    "sha": "5a9ef23eb2b6c8be2ebf0c636acfd92082292930",
    "html_url": "https://github.com/unb-mds/2025-2-Mural-UnB/commit/5a9ef23eb2b6c8be2ebf0c636acfd92082292930",
    "commit": {
      "author": {
        "name": "LucasFT",
        "email": "lucaasft16@gmail.com",
        "date": "2025-11-30T16:52:49-03:00",
        "login": "Lucasft16"
      },
      "committer": {
        "name": "LucasFT",
        "email": "lucaasft16@gmail.com",
        "date": "2025-11-30T19:52:49Z",
        "login": "Lucasft16"
      },
      "message": "fix: fix nas rotas das imagens"
    },
    "additions": 85,
    "deletions": 8,
    "total_changes": 93,
    "repo_name": "2025-2-Mural-UnB"
  },
  {
    "sha": "82d8eee44c85f0849506a8ca8fdbd992bdddb94c",
    "html_url": "https://github.com/unb-mds/2025-2-Mural-UnB/commit/82d8eee44c85f0849506a8ca8fdbd992bdddb94c",
    "commit": {
      "author": {
        "name": "LucasFT",
        "email": "lucaasft16@gmail.com",
        "date": "2025-11-30T16:44:05-03:00",
        "login": "Lucasft16"
      },
      "committer": {
        "name": "LucasFT",
        "email": "lucaasft16@gmail.com",
        "date": "2025-11-30T19:44:05Z",
        "login": "Lucasft16"
      },
      "message": "fix: fix para tags do pages"
    },
    "additions": 8,
    "deletions": 2,
    "total_changes": 10,
    "repo_name": "2025-2-Mural-UnB"
  },
  {
    "sha": "601d50b17e3ea9f26ec80bbfcc64ed08fefeef0f",
    "html_url": "https://github.com/unb-mds/2025-2-Mural-UnB/commit/601d50b17e3ea9f26ec80bbfcc64ed08fefeef0f",
    "commit": {
      "author": {
        "name": "LucasFT",
        "email": "lucaasft16@gmail.com",
        "date": "2025-11-30T16:36:21-03:00",
        "login": "Lucasft16"
      },
      "committer": {
        "name": "LucasFT",
        "email": "lucaasft16@gmail.com",
        "date": "2025-11-30T19:36:21Z",
        "login": "Lucasft16"
      },
      "message": "fix: fix no fetch das oportunidades"
    },
    "additions": 8,
    "deletions": 4,
    "total_changes": 12,
    "repo_name": "2025-2-Mural-UnB"
  },
  {
    "sha": "d5ef2624eab5e8c2ad50343fbda0cf450564cecc",
    "html_url": "https://github.com/unb-mds/2025-2-Mural-UnB/commit/d5ef2624eab5e8c2ad50343fbda0cf450564cecc",
    "commit": {
      "author": {
        "name": "LucasFT",
        "email": "lucaasft16@gmail.com",
        "date": "2025-11-30T16:28:46-03:00",
        "login": "Lucasft16"
      },
      "committer": {
        "name": "LucasFT",
        "email": "lucaasft16@gmail.com",
        "date": "2025-11-30T19:28:46Z",
        "login": "Lucasft16"
      },
      "message": "fix: fix dos links das oportunidades"
    },
    "additions": 15,
    "deletions": 12,
    "total_changes": 27,
    "repo_name": "2025-2-Mural-UnB"
  },
  {
    "sha": "6760b83164fb386f7e885ef5953f0bd8a6a2d3e1",
    "html_url": "https://github.com/unb-mds/2025-2-Mural-UnB/commit/6760b83164fb386f7e885ef5953f0bd8a6a2d3e1",
    "commit": {
      "author": {
        "name": "LucasFT",
        "email": "lucaasft16@gmail.com",
        "date": "2025-11-30T16:17:15-03:00",
        "login": "Lucasft16"
      },
      "committer": {
        "name": "LucasFT",
        "email": "lucaasft16@gmail.com",
        "date": "2025-11-30T19:17:15Z",
        "login": "Lucasft16"
      },
      "message": "fix: fix no deploy"
    },
    "additions": 8,
    "deletions": 7,
    "total_changes": 15,
    "repo_name": "2025-2-Mural-UnB"
  },
  {
    "sha": "cee88f5f651238d4f648ade7e677fd04c7e27273",
    "html_url": "https://github.com/unb-mds/2025-2-Mural-UnB/commit/cee88f5f651238d4f648ade7e677fd04c7e27273",
    "commit": {
      "author": {
        "name": "LucasFT",
        "email": "lucaasft16@gmail.com",
        "date": "2025-11-30T16:10:41-03:00",
        "login": "Lucasft16"
      },
      "committer": {
        "name": "LucasFT",
        "email": "lucaasft16@gmail.com",
        "date": "2025-11-30T19:10:41Z",
        "login": "Lucasft16"
      },
      "message": "fix: fix nas rotas do app"
    },
    "additions": 3,
    "deletions": 3,
    "total_changes": 6,
    "repo_name": "2025-2-Mural-UnB"
  },
  {
    "sha": "d2866e0b0dde738b06431c46a826a4f7b69c3872",
    "html_url": "https://github.com/unb-mds/2025-2-Mural-UnB/commit/d2866e0b0dde738b06431c46a826a4f7b69c3872",
    "commit": {
      "author": {
        "name": "Tiago Bittencourt",
        "email": "tiago.bittencourt.2005@gmail.com",
        "date": "2025-11-30T01:48:56-03:00",
        "login": "TiagoSBittencourt"
      },
      "committer": {
        "name": "Tiago Bittencourt",
        "email": "tiago.bittencourt.2005@gmail.com",
        "date": "2025-11-30T05:23:51Z",
        "login": "TiagoSBittencourt"
      },
      "message": "fix: index.html ref relativa incorreta para link"
    },
    "additions": 336,
    "deletions": 9,
    "total_changes": 345,
    "repo_name": "2025-2-Mural-UnB"
  },
  {
    "sha": "5d4302f7bdd0894db6c1f6f8ea67526798b47380",
    "html_url": "https://github.com/unb-mds/2025-2-Mural-UnB/commit/5d4302f7bdd0894db6c1f6f8ea67526798b47380",
    "commit": {
      "author": {
        "name": "Tiago Bittencourt",
        "email": "tiago.bittencourt.2005@gmail.com",
        "date": "2025-11-30T01:23:24-03:00",
        "login": "TiagoSBittencourt"
      },
      "committer": {
        "name": "GitHub",
        "email": "noreply@github.com",
        "date": "2025-11-30T04:23:24Z",
        "login": null
      },
      "message": "fix: Vite config para usar dynamic base URL (deploy)"
    },
    "additions": 9,
    "deletions": 9,
    "total_changes": 18,
    "repo_name": "2025-2-Mural-UnB"
  },
  {
    "sha": "6d6426a00b2e25a9df43408b36c1311349cbbab0",
    "html_url": "https://github.com/unb-mds/2025-2-Mural-UnB/commit/6d6426a00b2e25a9df43408b36c1311349cbbab0",
    "commit": {
      "author": {
        "name": "Tiago Bittencourt",
        "email": "tiago.bittencourt.2005@gmail.com",
        "date": "2025-11-30T01:16:34-03:00",
        "login": "TiagoSBittencourt"
      },
      "committer": {
        "name": "GitHub",
        "email": "noreply@github.com",
        "date": "2025-11-30T04:16:34Z",
        "login": null
      },
      "message": "fix: dependecy dir refs /site/ no deploy workflow"
    },
    "additions": 2,
    "deletions": 1,
    "total_changes": 3,
    "repo_name": "2025-2-Mural-UnB"
  },
  {
    "sha": "829cb3d5b85b4f725f7794f6a6c7e706afc1b381",
    "html_url": "https://github.com/unb-mds/2025-2-Mural-UnB/commit/829cb3d5b85b4f725f7794f6a6c7e706afc1b381",
    "commit": {
      "author": {
        "name": "Tiago Bittencourt",
        "email": "tiago.bittencourt.2005@gmail.com",
        "date": "2025-11-30T01:11:51-03:00",
        "login": "TiagoSBittencourt"
      },
      "committer": {
        "name": "GitHub",
        "email": "noreply@github.com",
        "date": "2025-11-30T04:11:51Z",
        "login": null
      },
      "message": "Merge pull request #139 from unb-mds/feat/deploy-site"
    },
    "additions": 393,
    "deletions": 120,
    "total_changes": 513,
    "repo_name": "2025-2-Mural-UnB"
  },
  {
    "sha": "6ad940a8970136c50fb9bad969913c9ef0e13077",
    "html_url": "https://github.com/unb-mds/2025-2-Mural-UnB/commit/6ad940a8970136c50fb9bad969913c9ef0e13077",
    "commit": {
      "author": {
        "name": "Tiago Bittencourt",
        "email": "tiago.bittencourt.2005@gmail.com",
        "date": "2025-11-30T00:58:11-03:00",
        "login": "TiagoSBittencourt"
      },
      "committer": {
        "name": "Tiago Bittencourt",
        "email": "tiago.bittencourt.2005@gmail.com",
        "date": "2025-11-30T03:58:11Z",
        "login": "TiagoSBittencourt"
      },
      "message": "chore: removi arquivos antigos de deploy"
    },
    "additions": 0,
    "deletions": 119,
    "total_changes": 119,
    "repo_name": "2025-2-Mural-UnB"
  },
  {
    "sha": "927f520354389cfbecfa058d7f8bbb5e361eacae",
    "html_url": "https://github.com/unb-mds/2025-2-Mural-UnB/commit/927f520354389cfbecfa058d7f8bbb5e361eacae",
    "commit": {
      "author": {
        "name": "Tiago Bittencourt",
        "email": "tiago.bittencourt.2005@gmail.com",
        "date": "2025-11-30T00:56:41-03:00",
        "login": "TiagoSBittencourt"
      },
      "committer": {
        "name": "Tiago Bittencourt",
        "email": "tiago.bittencourt.2005@gmail.com",
        "date": "2025-11-30T03:57:02Z",
        "login": "TiagoSBittencourt"
      },
      "message": "feat: novo workflow de deploy do site"
    },
    "additions": 393,
    "deletions": 1,
    "total_changes": 394,
    "repo_name": "2025-2-Mural-UnB"
  },
  {
    "sha": "2079972a2e1ed546a8243c62bd1b7d5f5829f65e",
    "html_url": "https://github.com/unb-mds/2025-2-Mural-UnB/commit/2079972a2e1ed546a8243c62bd1b7d5f5829f65e",
    "commit": {
      "author": {
        "name": "Tiago Bittencourt",
        "email": "tiago.bittencourt.2005@gmail.com",
        "date": "2025-11-29T23:56:00-03:00",
        "login": "TiagoSBittencourt"
      },
      "committer": {
        "name": "GitHub",
        "email": "noreply@github.com",
        "date": "2025-11-30T02:56:00Z",
        "login": null
      },
      "message": "Update navigation and section titles in README"
    },
    "additions": 6,
    "deletions": 4,
    "total_changes": 10,
    "repo_name": "2025-2-Mural-UnB"
  },
  {
    "sha": "b9cd253d65242b5a9829a377dd61e59ab5c72390",
    "html_url": "https://github.com/unb-mds/2025-2-Mural-UnB/commit/b9cd253d65242b5a9829a377dd61e59ab5c72390",
    "commit": {
      "author": {
        "name": "Tiago Bittencourt",
        "email": "tiago.bittencourt.2005@gmail.com",
        "date": "2025-11-29T23:53:41-03:00",
        "login": "TiagoSBittencourt"
      },
      "committer": {
        "name": "GitHub",
        "email": "noreply@github.com",
        "date": "2025-11-30T02:53:41Z",
        "login": null
      },
      "message": "Merge pull request #137 from unb-mds/docs/complete-review"
    },
    "additions": 65,
    "deletions": 34,
    "total_changes": 99,
    "repo_name": "2025-2-Mural-UnB"
  },
  {
    "sha": "296f40d84aed15b07b4ccec877cbb7c24ba519b2",
    "html_url": "https://github.com/unb-mds/2025-2-Mural-UnB/commit/296f40d84aed15b07b4ccec877cbb7c24ba519b2",
    "commit": {
      "author": {
        "name": "Tiago Bittencourt",
        "email": "tiago.bittencourt.2005@gmail.com",
        "date": "2025-11-29T23:49:24-03:00",
        "login": "TiagoSBittencourt"
      },
      "committer": {
        "name": "Tiago Bittencourt",
        "email": "tiago.bittencourt.2005@gmail.com",
        "date": "2025-11-30T02:49:24Z",
        "login": "TiagoSBittencourt"
      },
      "message": "docs(geral): atulizado a pagina geral e corrigi as mudancas arquitetu…"
    },
    "additions": 4,
    "deletions": 4,
    "total_changes": 8,
    "repo_name": "2025-2-Mural-UnB"
  },
  {
    "sha": "8e82578d5c53cd32d219bd75571c8337f72294ee",
    "html_url": "https://github.com/unb-mds/2025-2-Mural-UnB/commit/8e82578d5c53cd32d219bd75571c8337f72294ee",
    "commit": {
      "author": {
        "name": "Tiago Bittencourt",
        "email": "tiago.bittencourt.2005@gmail.com",
        "date": "2025-11-29T23:45:24-03:00",
        "login": "TiagoSBittencourt"
      },
      "committer": {
        "name": "Tiago Bittencourt",
        "email": "tiago.bittencourt.2005@gmail.com",
        "date": "2025-11-30T02:45:24Z",
        "login": "TiagoSBittencourt"
      },
      "message": "docs(security): adiconei o arquivo sobre a seguranca do repo"
    },
    "additions": 33,
    "deletions": 0,
    "total_changes": 33,
    "repo_name": "2025-2-Mural-UnB"
  },
  {
    "sha": "e389219fb16f67266951daadd9969f78938645ab",
    "html_url": "https://github.com/unb-mds/2025-2-Mural-UnB/commit/e389219fb16f67266951daadd9969f78938645ab",
    "commit": {
      "author": {
        "name": "Tiago Bittencourt",
        "email": "tiago.bittencourt.2005@gmail.com",
        "date": "2025-11-29T23:41:06-03:00",
        "login": "TiagoSBittencourt"
      },
      "committer": {
        "name": "Tiago Bittencourt",
        "email": "tiago.bittencourt.2005@gmail.com",
        "date": "2025-11-30T02:41:06Z",
        "login": "TiagoSBittencourt"
      },
      "message": "docs(nao-funcionais): atualizacao dos requisitos nao funcionais"
    },
    "additions": 7,
    "deletions": 11,
    "total_changes": 18,
    "repo_name": "2025-2-Mural-UnB"
  },
  {
    "sha": "5e90c357f681593879ce961447896f5ab3d88da5",
    "html_url": "https://github.com/unb-mds/2025-2-Mural-UnB/commit/5e90c357f681593879ce961447896f5ab3d88da5",
    "commit": {
      "author": {
        "name": "Tiago Bittencourt",
        "email": "tiago.bittencourt.2005@gmail.com",
        "date": "2025-11-29T23:35:51-03:00",
        "login": "TiagoSBittencourt"
      },
      "committer": {
        "name": "Tiago Bittencourt",
        "email": "tiago.bittencourt.2005@gmail.com",
        "date": "2025-11-30T02:35:51Z",
        "login": "TiagoSBittencourt"
      },
      "message": "docs(requisitos): atualizacao dos requisitos e US"
    },
    "additions": 8,
    "deletions": 2,
    "total_changes": 10,
    "repo_name": "2025-2-Mural-UnB"
  },
  {
    "sha": "a5ba5dcf51c4a9f92e0d0113128192ecd2c3cb68",
    "html_url": "https://github.com/unb-mds/2025-2-Mural-UnB/commit/a5ba5dcf51c4a9f92e0d0113128192ecd2c3cb68",
    "commit": {
      "author": {
        "name": "Tiago Bittencourt",
        "email": "tiago.bittencourt.2005@gmail.com",
        "date": "2025-11-29T23:30:21-03:00",
        "login": "TiagoSBittencourt"
      },
      "committer": {
        "name": "Tiago Bittencourt",
        "email": "tiago.bittencourt.2005@gmail.com",
        "date": "2025-11-30T02:30:21Z",
        "login": "TiagoSBittencourt"
      },
      "message": "docs: referencias adicionadas a pagina inicial"
    },
    "additions": 12,
    "deletions": 11,
    "total_changes": 23,
    "repo_name": "2025-2-Mural-UnB"
  },
  {
    "sha": "7c0b948de7c400df9206e44145b09d5fec269fdb",
    "html_url": "https://github.com/unb-mds/2025-2-Mural-UnB/commit/7c0b948de7c400df9206e44145b09d5fec269fdb",
    "commit": {
      "author": {
        "name": "Tiago Bittencourt",
        "email": "tiago.bittencourt.2005@gmail.com",
        "date": "2025-11-29T23:28:27-03:00",
        "login": "TiagoSBittencourt"
      },
      "committer": {
        "name": "Tiago Bittencourt",
        "email": "tiago.bittencourt.2005@gmail.com",
        "date": "2025-11-30T02:28:27Z",
        "login": "TiagoSBittencourt"
      },
      "message": "docs: atualizacao das tecnologias utilizadas"
    },
    "additions": 8,
    "deletions": 7,
    "total_changes": 15,
    "repo_name": "2025-2-Mural-UnB"
  },
  {
    "sha": "43f32bedf743a6f96213942397bc6c745ef9ab03",
    "html_url": "https://github.com/unb-mds/2025-2-Mural-UnB/commit/43f32bedf743a6f96213942397bc6c745ef9ab03",
    "commit": {
      "author": {
        "name": "Tiago Bittencourt",
        "email": "tiago.bittencourt.2005@gmail.com",
        "date": "2025-11-29T23:24:52-03:00",
        "login": "TiagoSBittencourt"
      },
      "committer": {
        "name": "Tiago Bittencourt",
        "email": "tiago.bittencourt.2005@gmail.com",
        "date": "2025-11-30T02:24:52Z",
        "login": "TiagoSBittencourt"
      },
      "message": "docs(fix): removi duplicata na parte de rabbit"
    },
    "additions": 0,
    "deletions": 6,
    "total_changes": 6,
    "repo_name": "2025-2-Mural-UnB"
  },
  {
    "sha": "5dee1392e879c97768a32c639f7b192f5058a51a",
    "html_url": "https://github.com/unb-mds/2025-2-Mural-UnB/commit/5dee1392e879c97768a32c639f7b192f5058a51a",
    "commit": {
      "author": {
        "name": "Lucas Fujimoto Tokunaga",
        "email": "lucaasft16@gmail.com",
        "date": "2025-11-29T22:51:37-03:00",
        "login": "Lucasft16"
      },
      "committer": {
        "name": "GitHub",
        "email": "noreply@github.com",
        "date": "2025-11-30T01:51:37Z",
        "login": null
      },
      "message": "Merge pull request #136 from unb-mds/paginas"
    },
    "additions": 182,
    "deletions": 4,
    "total_changes": 186,
    "repo_name": "2025-2-Mural-UnB"
  },
  {
    "sha": "e0ec3d8ee0ec56cdbb4e61a80c222a5947a2c7f2",
    "html_url": "https://github.com/unb-mds/2025-2-Mural-UnB/commit/e0ec3d8ee0ec56cdbb4e61a80c222a5947a2c7f2",
    "commit": {
      "author": {
        "name": "LucasFT",
        "email": "lucaasft16@gmail.com",
        "date": "2025-11-29T22:44:20-03:00",
        "login": "Lucasft16"
      },
      "committer": {
        "name": "LucasFT",
        "email": "lucaasft16@gmail.com",
        "date": "2025-11-30T01:44:20Z",
        "login": "Lucasft16"
      },
      "message": "feat:Adição da lógica de paginação #135"
    },
    "additions": 182,
    "deletions": 4,
    "total_changes": 186,
    "repo_name": "2025-2-Mural-UnB"
  },
  {
    "sha": "e8a88f75ee4e3c4e1b4a2cc08d4aec9a8d9e4a45",
    "html_url": "https://github.com/unb-mds/2025-2-Mural-UnB/commit/e8a88f75ee4e3c4e1b4a2cc08d4aec9a8d9e4a45",
    "commit": {
      "author": {
        "name": "Lucas Fujimoto Tokunaga",
        "email": "lucaasft16@gmail.com",
        "date": "2025-11-28T14:27:33-03:00",
        "login": "Lucasft16"
      },
      "committer": {
        "name": "GitHub",
        "email": "noreply@github.com",
        "date": "2025-11-28T17:27:33Z",
        "login": null
      },
      "message": "fix no requesitos funcionais"
    },
    "additions": 23,
    "deletions": 11,
    "total_changes": 34,
    "repo_name": "2025-2-Mural-UnB"
  },
  {
    "sha": "2029be469a8de748f6df63a723242bfaa8a52b6b",
    "html_url": "https://github.com/unb-mds/2025-2-Mural-UnB/commit/2029be469a8de748f6df63a723242bfaa8a52b6b",
    "commit": {
      "author": {
        "name": "LucasFT",
        "email": "lucaasft16@gmail.com",
        "date": "2025-11-28T14:26:21-03:00",
        "login": "Lucasft16"
      },
      "committer": {
        "name": "LucasFT",
        "email": "lucaasft16@gmail.com",
        "date": "2025-11-28T17:26:21Z",
        "login": "Lucasft16"
      },
      "message": "fix: fix no requesitos funcionais"
    },
    "additions": 23,
    "deletions": 11,
    "total_changes": 34,
    "repo_name": "2025-2-Mural-UnB"
  },
  {
    "sha": "1a6f4bbf609d2f52e25d38cec8d50a43cded1b1b",
    "html_url": "https://github.com/unb-mds/2025-2-Mural-UnB/commit/1a6f4bbf609d2f52e25d38cec8d50a43cded1b1b",
    "commit": {
      "author": {
        "name": "Maria",
        "email": "232005352@aluno.unb.br",
        "date": "2025-11-28T14:06:05-03:00",
        "login": "MariaClara-Canuto"
      },
      "committer": {
        "name": "GitHub",
        "email": "noreply@github.com",
        "date": "2025-11-28T17:06:05Z",
        "login": null
      },
      "message": "Erro no arquitetura-front.md"
    },
    "additions": 4,
    "deletions": 6,
    "total_changes": 10,
    "repo_name": "2025-2-Mural-UnB"
  },
  {
    "sha": "32d7956cbfb303254bd2475cae80d8c892e39cea",
    "html_url": "https://github.com/unb-mds/2025-2-Mural-UnB/commit/32d7956cbfb303254bd2475cae80d8c892e39cea",
    "commit": {
      "author": {
        "name": "Maria Clara",
        "email": "232005352@aluno.unb.br",
        "date": "2025-11-28T13:59:16-03:00",
        "login": "MariaClara-Canuto"
      },
      "committer": {
        "name": "Maria Clara",
        "email": "232005352@aluno.unb.br",
        "date": "2025-11-28T16:59:16Z",
        "login": "MariaClara-Canuto"
      },
      "message": "Task: Adicionado nova arquitetura do Front-End #132"
    },
    "additions": 88,
    "deletions": 34,
    "total_changes": 122,
    "repo_name": "2025-2-Mural-UnB"
  },
  {
    "sha": "0833dded609823dcbed562c9a34c24c6e4103eaf",
    "html_url": "https://github.com/unb-mds/2025-2-Mural-UnB/commit/0833dded609823dcbed562c9a34c24c6e4103eaf",
    "commit": {
      "author": {
        "name": "Lucas Fujimoto Tokunaga",
        "email": "lucaasft16@gmail.com",
        "date": "2025-11-27T20:01:33-03:00",
        "login": "Lucasft16"
      },
      "committer": {
        "name": "GitHub",
        "email": "noreply@github.com",
        "date": "2025-11-27T23:01:33Z",
        "login": null
      },
      "message": "Merge pull request #131 from unb-mds/docscom"
    },
    "additions": 29,
    "deletions": 92,
    "total_changes": 121,
    "repo_name": "2025-2-Mural-UnB"
  },
  {
    "sha": "652f456ffa01dcfb432863b5e555d28279f0ed42",
    "html_url": "https://github.com/unb-mds/2025-2-Mural-UnB/commit/652f456ffa01dcfb432863b5e555d28279f0ed42",
    "commit": {
      "author": {
        "name": "LucasFT",
        "email": "lucaasft16@gmail.com",
        "date": "2025-11-27T19:59:06-03:00",
        "login": "Lucasft16"
      },
      "committer": {
        "name": "LucasFT",
        "email": "lucaasft16@gmail.com",
        "date": "2025-11-27T22:59:06Z",
        "login": "Lucasft16"
      },
      "message": "fix: ajuste no docs de requisitos funcionais para alinhar com a docum…"
    },
    "additions": 29,
    "deletions": 92,
    "total_changes": 121,
    "repo_name": "2025-2-Mural-UnB"
  },
  {
    "sha": "1c5a13d007cc5d5470614783e87cdbf9cabc9c15",
    "html_url": "https://github.com/unb-mds/2025-2-Mural-UnB/commit/1c5a13d007cc5d5470614783e87cdbf9cabc9c15",
    "commit": {
      "author": {
        "name": "Tiago Bittencourt",
        "email": "tiago.bittencourt.2005@gmail.com",
        "date": "2025-11-25T22:33:27-03:00",
        "login": "TiagoSBittencourt"
      },
      "committer": {
        "name": "GitHub",
        "email": "noreply@github.com",
        "date": "2025-11-26T01:33:27Z",
        "login": null
      },
      "message": "fix(readme): formatação do comando clone na instalação"
    },
    "additions": 1,
    "deletions": 1,
    "total_changes": 2,
    "repo_name": "2025-2-Mural-UnB"
  },
  {
    "sha": "df7aac2702a53900d7d50143850c891e3279b818",
    "html_url": "https://github.com/unb-mds/2025-2-Mural-UnB/commit/df7aac2702a53900d7d50143850c891e3279b818",
    "commit": {
      "author": {
        "name": "Matheus Saraiva Camargo",
        "email": "128329654+apptrx@users.noreply.github.com",
        "date": "2025-11-25T22:04:33-03:00",
        "login": "apptrx"
      },
      "committer": {
        "name": "GitHub",
        "email": "noreply@github.com",
        "date": "2025-11-26T01:04:33Z",
        "login": null
      },
      "message": "Merge pull request #130 from unb-mds/docs/documentacao-tecnica"
    },
    "additions": 171,
    "deletions": 24,
    "total_changes": 195,
    "repo_name": "2025-2-Mural-UnB"
  },
  {
    "sha": "1bf9704aa4dc60f196cf2f7cfca97a474b3310da",
    "html_url": "https://github.com/unb-mds/2025-2-Mural-UnB/commit/1bf9704aa4dc60f196cf2f7cfca97a474b3310da",
    "commit": {
      "author": {
        "name": "apptrx",
        "email": "matheusscamargo13@gmail.com",
        "date": "2025-11-25T21:32:12-03:00",
        "login": "apptrx"
      },
      "committer": {
        "name": "apptrx",
        "email": "matheusscamargo13@gmail.com",
        "date": "2025-11-26T00:32:12Z",
        "login": "apptrx"
      },
      "message": "docs: Adiciona links para documentação técnica no README principal (#…"
    },
    "additions": 25,
    "deletions": 0,
    "total_changes": 25,
    "repo_name": "2025-2-Mural-UnB"
  },
  {
    "sha": "8a02175c540c3eb5a3c75ade82ee3d4d69ff3f68",
    "html_url": "https://github.com/unb-mds/2025-2-Mural-UnB/commit/8a02175c540c3eb5a3c75ade82ee3d4d69ff3f68",
    "commit": {
      "author": {
        "name": "apptrx",
        "email": "matheusscamargo13@gmail.com",
        "date": "2025-11-25T21:25:41-03:00",
        "login": "apptrx"
      },
      "committer": {
        "name": "apptrx",
        "email": "matheusscamargo13@gmail.com",
        "date": "2025-11-26T00:25:41Z",
        "login": "apptrx"
      },
      "message": "docs: Guia de scripts (#113)"
    },
    "additions": 88,
    "deletions": 25,
    "total_changes": 113,
    "repo_name": "2025-2-Mural-UnB"
  },
  {
    "sha": "4984d5226e14f6051a956d9c5e3249d8c38b74fd",
    "html_url": "https://github.com/unb-mds/2025-2-Mural-UnB/commit/4984d5226e14f6051a956d9c5e3249d8c38b74fd",
    "commit": {
      "author": {
        "name": "apptrx",
        "email": "matheusscamargo13@gmail.com",
        "date": "2025-11-25T20:32:51-03:00",
        "login": "apptrx"
      },
      "committer": {
        "name": "apptrx",
        "email": "matheusscamargo13@gmail.com",
        "date": "2025-11-25T23:32:51Z",
        "login": "apptrx"
      },
      "message": "test: Adiciona mocks de download (requests) e file system (open) para…"
    },
    "additions": 25,
    "deletions": 16,
    "total_changes": 41,
    "repo_name": "2025-2-Mural-UnB"
  },
  {
    "sha": "c7435891392edc116851e18044c43254c0acf706",
    "html_url": "https://github.com/unb-mds/2025-2-Mural-UnB/commit/c7435891392edc116851e18044c43254c0acf706",
    "commit": {
      "author": {
        "name": "apptrx",
        "email": "matheusscamargo13@gmail.com",
        "date": "2025-11-25T20:16:50-03:00",
        "login": "apptrx"
      },
      "committer": {
        "name": "apptrx",
        "email": "matheusscamargo13@gmail.com",
        "date": "2025-11-25T23:16:50Z",
        "login": "apptrx"
      },
      "message": "docs: Documenta estrutura de dados, CSVs e artefatos de IA (#113)"
    },
    "additions": 33,
    "deletions": 0,
    "total_changes": 33,
    "repo_name": "2025-2-Mural-UnB"
  },
  {
    "sha": "2b6d003a14e03f473d7ef276c7d794813168d424",
    "html_url": "https://github.com/unb-mds/2025-2-Mural-UnB/commit/2b6d003a14e03f473d7ef276c7d794813168d424",
    "commit": {
      "author": {
        "name": "apptrx",
        "email": "matheusscamargo13@gmail.com",
        "date": "2025-11-25T20:15:07-03:00",
        "login": "apptrx"
      },
      "committer": {
        "name": "apptrx",
        "email": "matheusscamargo13@gmail.com",
        "date": "2025-11-25T23:15:07Z",
        "login": "apptrx"
      },
      "message": "docs: Adiciona política de segurança e reporte de vulnerabilidades (#…"
    },
    "additions": 17,
    "deletions": 0,
    "total_changes": 17,
    "repo_name": "2025-2-Mural-UnB"
  },
  {
    "sha": "e8341f12b94080e150ed57d6bb43b683da8bf1cd",
    "html_url": "https://github.com/unb-mds/2025-2-Mural-UnB/commit/e8341f12b94080e150ed57d6bb43b683da8bf1cd",
    "commit": {
      "author": {
        "name": "apptrx",
        "email": "matheusscamargo13@gmail.com",
        "date": "2025-11-25T19:58:32-03:00",
        "login": "apptrx"
      },
      "committer": {
        "name": "apptrx",
        "email": "matheusscamargo13@gmail.com",
        "date": "2025-11-25T22:58:32Z",
        "login": "apptrx"
      },
      "message": "docs: Adiciona documentação técnica (Security, Dados e Scripts) (#113)"
    },
    "additions": 0,
    "deletions": 0,
    "total_changes": 0,
    "repo_name": "2025-2-Mural-UnB"
  },
  {
    "sha": "107ee88b00d435766a6c66150de94cece4a90e11",
    "html_url": "https://github.com/unb-mds/2025-2-Mural-UnB/commit/107ee88b00d435766a6c66150de94cece4a90e11",
    "commit": {
      "author": {
        "name": "Lucas Fujimoto Tokunaga",
        "email": "lucaasft16@gmail.com",
        "date": "2025-11-24T15:07:32-03:00",
        "login": "Lucasft16"
      },
      "committer": {
        "name": "GitHub",
        "email": "noreply@github.com",
        "date": "2025-11-24T18:07:32Z",
        "login": null
      },
      "message": "Merge pull request #129 from unb-mds/docscom"
    },
    "additions": 80,
    "deletions": 35,
    "total_changes": 115,
    "repo_name": "2025-2-Mural-UnB"
  },
  {
    "sha": "7c79fdedca0ca22bc373a3f9d7f4beb351c0b927",
    "html_url": "https://github.com/unb-mds/2025-2-Mural-UnB/commit/7c79fdedca0ca22bc373a3f9d7f4beb351c0b927",
    "commit": {
      "author": {
        "name": "LucasFT",
        "email": "lucaasft16@gmail.com",
        "date": "2025-11-24T15:01:14-03:00",
        "login": "Lucasft16"
      },
      "committer": {
        "name": "LucasFT",
        "email": "lucaasft16@gmail.com",
        "date": "2025-11-24T18:01:14Z",
        "login": "Lucasft16"
      },
      "message": "fix: atualizacao do security e code of conduct"
    },
    "additions": 61,
    "deletions": 40,
    "total_changes": 101,
    "repo_name": "2025-2-Mural-UnB"
  },
  {
    "sha": "4c4ec42d23547087cfcfd392a4d233c8a8d7598b",
    "html_url": "https://github.com/unb-mds/2025-2-Mural-UnB/commit/4c4ec42d23547087cfcfd392a4d233c8a8d7598b",
    "commit": {
      "author": {
        "name": "LucasFT",
        "email": "lucaasft16@gmail.com",
        "date": "2025-11-24T14:41:36-03:00",
        "login": "Lucasft16"
      },
      "committer": {
        "name": "LucasFT",
        "email": "lucaasft16@gmail.com",
        "date": "2025-11-24T17:41:49Z",
        "login": "Lucasft16"
      },
      "message": "task: Adição do security.md primario (sem o email de contato) #113"
    },
    "additions": 24,
    "deletions": 0,
    "total_changes": 24,
    "repo_name": "2025-2-Mural-UnB"
  },
  {
    "sha": "44de0fe6166761e8d381a4b2b17b6f2b069cb01b",
    "html_url": "https://github.com/unb-mds/2025-2-Mural-UnB/commit/44de0fe6166761e8d381a4b2b17b6f2b069cb01b",
    "commit": {
      "author": {
        "name": "João Gonzaga",
        "email": "165739233+Karmantinedev@users.noreply.github.com",
        "date": "2025-11-23T18:38:34-03:00",
        "login": "Karmantinedev"
      },
      "committer": {
        "name": "GitHub",
        "email": "noreply@github.com",
        "date": "2025-11-23T21:38:34Z",
        "login": null
      },
      "message": "Merge pull request #123 from unb-mds/testes-scripts-EJs"
    },
    "additions": 2027,
    "deletions": 125,
    "total_changes": 2152,
    "repo_name": "2025-2-Mural-UnB"
  },
  {
    "sha": "02817910199ffa9cdff82494b7295ec8f2e1fc36",
    "html_url": "https://github.com/unb-mds/2025-2-Mural-UnB/commit/02817910199ffa9cdff82494b7295ec8f2e1fc36",
    "commit": {
      "author": {
        "name": "Lucasft16",
        "email": "lucaasft16@gmail.com",
        "date": "2025-11-23T01:58:41Z",
        "login": "Lucasft16"
      },
      "committer": {
        "name": "João Gonzaga",
        "email": "gonzagajp17@gmail.com",
        "date": "2025-11-23T21:32:18Z",
        "login": "Karmantinedev"
      },
      "message": "chore: atualizar dados empresas juniores (49 empresas) [skip ci]"
    },
    "additions": 93,
    "deletions": 93,
    "total_changes": 186,
    "repo_name": "2025-2-Mural-UnB"
  },
  {
    "sha": "0ae1fbab7a9bbd17f4bd797214aed7cdab0aeefb",
    "html_url": "https://github.com/unb-mds/2025-2-Mural-UnB/commit/0ae1fbab7a9bbd17f4bd797214aed7cdab0aeefb",
    "commit": {
      "author": {
        "name": "João Gonzaga",
        "email": "gonzagajp17@gmail.com",
        "date": "2025-11-22T22:54:24-03:00",
        "login": "Karmantinedev"
      },
      "committer": {
        "name": "João Gonzaga",
        "email": "gonzagajp17@gmail.com",
        "date": "2025-11-23T21:32:17Z",
        "login": "Karmantinedev"
      },
      "message": "update requerimentos EJs"
    },
    "additions": 7,
    "deletions": 6,
    "total_changes": 13,
    "repo_name": "2025-2-Mural-UnB"
  }
]