{
  "login": "jpcfarias",
  "id": 65802222,
  "node_id": "MDQ6VXNlcjY1ODAyMjIy",
  "avatar_url": "https://avatars.githubusercontent.com/u/65802222?v=4",
  "gravatar_id": "",
  "url": "https://api.github.com/users/jpcfarias",
  "html_url": "https://github.com/jpcfarias",
  "followers_url": "https://api.github.com/users/jpcfarias/followers",
  "following_url": "https://api.github.com/users/jpcfarias/following{/other_user}",
  "gists_url": "https://api.github.com/users/jpcfarias/gists{/gist_id}",
  "starred_url": "https://api.github.com/users/jpcfarias/starred{/owner}{/repo}",
  "subscriptions_url": "https://api.github.com/users/jpcfarias/subscriptions",
  "organizations_url": "https://api.github.com/users/jpcfarias/orgs",
  "repos_url": "https://api.github.com/users/jpcfarias/repos",
  "events_url": "https://api.github.com/users/jpcfarias/events{/privacy}",
  "received_events_url": "https://api.github.com/users/jpcfarias/received_events",
  "type": "User",
  "user_view_type": "public",
  "site_admin": false,
  "name": "Joao Farias",
  "company": null,
  "blog": "",
  "location": "Brasília,DF",
  "email": "contato.joao.farias@gmail.com",
  "hireable": null,
  "bio": "Engenharia de Software - UnB    ",
  "twitter_username": null,
  "public_repos": 17,
  "public_gists": 1,
  "followers": 17,
  "following": 12,
  "created_at": "2020-05-23T05:19:22Z",
  "updated_at": "2025-10-15T00:57:09Z",
  "_metadata": {
    "extracted_at": "2025-10-18T00:05:40.215121",
    "file_path": "data/bronze/member_jpcfarias.json"
  }
}