{
  "login": "DanielFsR",
  "id": 118537519,
  "node_id": "U_kgDOBxC9Lw",
  "avatar_url": "https://avatars.githubusercontent.com/u/118537519?v=4",
  "gravatar_id": "",
  "url": "https://api.github.com/users/DanielFsR",
  "html_url": "https://github.com/DanielFsR",
  "followers_url": "https://api.github.com/users/DanielFsR/followers",
  "following_url": "https://api.github.com/users/DanielFsR/following{/other_user}",
  "gists_url": "https://api.github.com/users/DanielFsR/gists{/gist_id}",
  "starred_url": "https://api.github.com/users/DanielFsR/starred{/owner}{/repo}",
  "subscriptions_url": "https://api.github.com/users/DanielFsR/subscriptions",
  "organizations_url": "https://api.github.com/users/DanielFsR/orgs",
  "repos_url": "https://api.github.com/users/DanielFsR/repos",
  "events_url": "https://api.github.com/users/DanielFsR/events{/privacy}",
  "received_events_url": "https://api.github.com/users/DanielFsR/received_events",
  "type": "User",
  "user_view_type": "public",
  "site_admin": false,
  "name": "Daniel Ferreira Santos Rabelo",
  "company": "UNB",
  "blog": "",
  "location": "Brasilia-DF",
  "email": null,
  "hireable": null,
  "bio": "Estudante",
  "twitter_username": null,
  "public_repos": 5,
  "public_gists": 0,
  "followers": 7,
  "following": 7,
  "created_at": "2022-11-18T12:42:34Z",
  "updated_at": "2025-10-08T10:47:10Z",
  "_metadata": {
    "extracted_at": "2025-10-18T00:05:40.216860",
    "file_path": "data/bronze/member_DanielFsR.json"
  }
}