[
  {
    "_metadata": {
      "extracted_at": "2026-01-17T05:52:57.776594",
      "file_path": "data/silver/repository_collaboration_analysis.json",
      "record_count": 73
    }
  },
  {
    "repo": "FixIt",
    "contributor_count": 51,
    "contributors": [
      "github-actions[bot]",
      "edte",
      "rsrchboy",
      "thejayhaykid",
      "Fastbyte01",
      "asaraog",
      "tomaja-linuxo",
      "dependabot[bot]",
      "Xm798",
      "hiifong",
      "anup92k",
      "yureiita",
      "mathieu-gilloots",
      "SilkeHenderickx",
      "ramrodo",
      "stefanoginobili",
      "Kapusch",
      "dillonzq",
      "dogukanerel",
      "Mejituu",
      "Lruihao",
      "ych817",
      "codedge",
      "xueweiwujxw",
      "0x020B",
      "youngxhui",
      "tlereste",
      "ziobron",
      "NicoDreamzZ",
      "pandaoh",
      "victor-pogor",
      "DaveA-W",
      "devandreacarratta",
      "solarpowerinncr",
      "sarathsp06",
      "nikuleo",
      "wtchangdm",
      "AliSajid",
      "vanildosouto",
      "quyleanh",
      "Fedomn",
      "psi59",
      "StarryReverie",
      "DimmKirr",
      "Ryaang",
      "navjotjsingh",
      "cmpsoares91",
      "will4j",
      "Programazing",
      "onisuly",
      "astropenguin"
    ],
    "potential_collaborations": 1275,
    "actual_collaborations": 1275,
    "collaboration_density": 1.0
  },
  {
    "repo": "hugoplate",
    "contributor_count": 23,
    "contributors": [
      "jmMeessen",
      "ytrepidorosonomous",
      "deining",
      "tfsojon",
      "teamosishq",
      "sapradhan",
      "tfsomrat",
      "othernotherone",
      "rafafrdz",
      "1gcat",
      "DipeshAggarwal",
      "ssojonn",
      "alexgutjahr",
      "regtm",
      "preston-bernstein",
      "tfrubel",
      "leoliu0605",
      "junnei",
      "tfsumon",
      "arijitlaik",
      "tffarhad",
      "mbrejla",
      "rpoisel"
    ],
    "potential_collaborations": 253,
    "actual_collaborations": 253,
    "collaboration_density": 1.0
  },
  {
    "repo": "Qualifying-Software-Engineers-Undergraduates-in-DevOps",
    "contributor_count": 21,
    "contributors": [
      "LeoSilvaGomes",
      "RochaCarla",
      "luccameds",
      "ana-pfeilsticker",
      "Mylena-angelica",
      "bot-do-jao",
      "gabrielm2q",
      "PhFariaa",
      "zlimaz",
      "mat054",
      "Ninja-Haiyai",
      "Mateushqms",
      "alvesisaque",
      "guilhermedelyra",
      "Beatriz-ge",
      "BrunoBReis",
      "rafgpereira",
      "joycedio",
      "MariaCHelena",
      "Discicle",
      "thaleseuflauzino"
    ],
    "potential_collaborations": 210,
    "actual_collaborations": 210,
    "collaboration_density": 1.0
  },
  {
    "repo": "Avalia",
    "contributor_count": 20,
    "contributors": [
      "MarcusVRezende",
      "RochaCarla",
      "Romm-0",
      "filipeBG-07",
      "Jp-te",
      "Karmantinedev",
      "Fofodoido",
      "JoaoGSantana10",
      "MariaClara-Canuto",
      "Phill-Chill",
      "brunodantas9",
      "Lucasft16",
      "gpaulovit",
      "Flyxs",
      "ananunesv",
      "menali17",
      "HugoFreitass",
      "PedroGTG",
      "guxvr",
      "pedruck"
    ],
    "potential_collaborations": 190,
    "actual_collaborations": 190,
    "collaboration_density": 1.0
  },
  {
    "repo": "2023-2-SuaGradeUnB",
    "contributor_count": 17,
    "contributors": [
      "artrsousa1",
      "LuisMiranda10",
      "mateusvrs",
      "vercel[bot]",
      "sluucke",
      "lucasqueiroz23",
      "RA-Salles",
      "FelipeFranke5",
      "henriquecq",
      "CaioHabibe",
      "RochaCarla",
      "dependabot[bot]",
      "GabrielCastelo-31",
      "ingrdsoares",
      "fsousac",
      "melohugo",
      "caio-felipee"
    ],
    "potential_collaborations": 136,
    "actual_collaborations": 136,
    "collaboration_density": 1.0
  },
  {
    "repo": "2024-2-AcheiUnB",
    "contributor_count": 17,
    "contributors": [
      "arthurevg",
      "Dannyeclisson",
      "github-project-automation[bot]",
      "Davicamilo23",
      "brunnoff",
      "cibelinda",
      "Potatoyz908",
      "leoramiroo",
      "anaelisaramos",
      "pedroeverton217",
      "RochaCarla",
      "dependabot[bot]",
      "ZarbL",
      "igorvdaniel",
      "314dro",
      "TiagoBalieiro",
      "zlimaz"
    ],
    "potential_collaborations": 136,
    "actual_collaborations": 136,
    "collaboration_density": 1.0
  },
  {
    "repo": "2025-1-NoFluxoUNB",
    "contributor_count": 13,
    "contributors": [
      "hisarxt",
      "staann",
      "github-project-automation[bot]",
      "erickaalves",
      "gusmoles",
      "darkymeubem",
      "WallaceBarrosDev",
      "Vitor-Trancoso",
      "RochaCarla",
      "ArthurNRamalho",
      "Wallacebarros",
      "Vinicius-Ribeiro04",
      "knz13"
    ],
    "potential_collaborations": 78,
    "actual_collaborations": 78,
    "collaboration_density": 1.0
  },
  {
    "repo": "2025-2-Squad-01",
    "contributor_count": 12,
    "contributors": [
      "cadumotta",
      "danrleypereira",
      "github-actions[bot]",
      "pedrogrocha13",
      "Copilot",
      "RochaCarla",
      "Gustavo",
      "HeitorM50",
      "Marcs2608",
      "guxvr",
      "pedruck",
      "Carla Rocha"
    ],
    "potential_collaborations": 66,
    "actual_collaborations": 66,
    "collaboration_density": 1.0
  },
  {
    "repo": "2023-2-Squad03-LicitAL",
    "contributor_count": 11,
    "contributors": [
      "github-project-automation[bot]",
      "joycejdm",
      "DiegoSousaLeite",
      "RochaCarla",
      "EstherSousa",
      "MarcoTulioSoares",
      "brunocva",
      "Paxxaglia",
      "M4RINH0",
      "joycedio",
      "PedroHenrique061"
    ],
    "potential_collaborations": 55,
    "actual_collaborations": 55,
    "collaboration_density": 1.0
  },
  {
    "repo": "LicitaBSB-24.1",
    "contributor_count": 11,
    "contributors": [
      "nateejpg",
      "github-project-automation[bot]",
      "thaleseuflauzino",
      "walbarellos",
      "RochaCarla",
      "m4rllon",
      "actions",
      "Marcelo-Adrian",
      "MariaCHelena",
      "Otavio4283",
      "moonshinerd"
    ],
    "potential_collaborations": 55,
    "actual_collaborations": 55,
    "collaboration_density": 1.0
  },
  {
    "repo": "DFemObras-2025.1",
    "contributor_count": 11,
    "contributors": [
      "github-actions[bot]",
      "github-project-automation[bot]",
      "Copilot",
      "RochaCarla",
      "BeatrizSants",
      "Samuel-A-Santos",
      "Antedeguemon21",
      "laurarogelin",
      "PedroHenriqueCo",
      "Heloisa-Santos",
      "LORliveira"
    ],
    "potential_collaborations": 55,
    "actual_collaborations": 55,
    "collaboration_density": 1.0
  },
  {
    "repo": "VIDAProject",
    "contributor_count": 11,
    "contributors": [
      "github-project-automation[bot]",
      "gsVieiraaa",
      "EduardoRGS",
      "RochaCarla",
      "vhcsdev",
      "Pablo-R-L",
      "leticia-oliveira",
      "unb-mds",
      "Rukkakun",
      "osakareaper",
      "pratamz250"
    ],
    "potential_collaborations": 55,
    "actual_collaborations": 55,
    "collaboration_density": 1.0
  },
  {
    "repo": "2023-2-Squad02-Desmatazonia",
    "contributor_count": 10,
    "contributors": [
      "acamposs",
      "souzagusta",
      "github-project-automation[bot]",
      "RochaCarla",
      "SkywalkerSupreme",
      "Carlos42511",
      "IsaqueSH",
      "Angelicahaas",
      "alanagabriele",
      "daramariabs"
    ],
    "potential_collaborations": 45,
    "actual_collaborations": 45,
    "collaboration_density": 1.0
  },
  {
    "repo": "2023-2-JuizVirtual",
    "contributor_count": 10,
    "contributors": [
      "github-project-automation[bot]",
      "MMcLovin",
      "RochaCarla",
      "EstherSousa",
      "LuizaMaluf",
      "dependabot[bot]",
      "jpcfarias",
      "HladczukLe",
      "thegm445",
      "bitterteriyaki"
    ],
    "potential_collaborations": 45,
    "actual_collaborations": 45,
    "collaboration_density": 1.0
  },
  {
    "repo": "2023.2_DeOlhoRS",
    "contributor_count": 10,
    "contributors": [
      "savioc2",
      "anabborges",
      "cqcoding",
      "vercel[bot]",
      "RochaCarla",
      "vitorfleonardo",
      "VieiraLaris",
      "BiancaPatrocinio7",
      "matheusbmello",
      "BrunoHDuarte2"
    ],
    "potential_collaborations": 45,
    "actual_collaborations": 45,
    "collaboration_density": 1.0
  },
  {
    "repo": "2024-2-Squad06",
    "contributor_count": 10,
    "contributors": [
      "Neoprot",
      "vercel[bot]",
      "TiagoTeixeira-2005",
      "NayraNery127",
      "railway-app[bot]",
      "RochaCarla",
      "dependabot[bot]",
      "ArthurGuilher62",
      "Ana-Luiza-SC",
      "alvesingrid"
    ],
    "potential_collaborations": 45,
    "actual_collaborations": 45,
    "collaboration_density": 1.0
  },
  {
    "repo": "mapadaacessibilidade",
    "contributor_count": 10,
    "contributors": [
      "github-project-automation[bot]",
      "oalbertocavalcante",
      "Maria-Laura-Regis",
      "code-silva",
      "Dexmachi",
      "RochaCarla",
      "Samuelvlobo",
      "Lucas-Ricarte",
      "user",
      "CaioSoandrd"
    ],
    "potential_collaborations": 45,
    "actual_collaborations": 45,
    "collaboration_density": 1.0
  },
  {
    "repo": "ParticipeMais",
    "contributor_count": 10,
    "contributors": [
      "github-project-automation[bot]",
      "Szervinsk",
      "GGDornelas",
      "camposs04",
      "SchneiderCode1",
      "RochaCarla",
      "dependabot[bot]",
      "phenric26",
      "jpnunes2210",
      "y123yuri"
    ],
    "potential_collaborations": 45,
    "actual_collaborations": 45,
    "collaboration_density": 1.0
  },
  {
    "repo": "Sonorus-2025.1",
    "contributor_count": 10,
    "contributors": [
      "luannvi",
      "github-project-automation[bot]",
      "Pauloswimming",
      "Dodeglinhass",
      "JoaquimNetoo",
      "rafaelbdmelo117",
      "RochaCarla",
      "dtdanielteles",
      "matheuslemesam",
      "Pnery2004"
    ],
    "potential_collaborations": 45,
    "actual_collaborations": 45,
    "collaboration_density": 1.0
  },
  {
    "repo": "2025-1-GovInsights",
    "contributor_count": 10,
    "contributors": [
      "Lithuania0",
      "Brwnds",
      "github-project-automation[bot]",
      "mariadenis",
      "GFlyan",
      "RochaCarla",
      "GabrielMacielBR",
      "EricAraujoBsB",
      "Marjoriemitzi",
      "eduardar0"
    ],
    "potential_collaborations": 45,
    "actual_collaborations": 45,
    "collaboration_density": 1.0
  },
  {
    "repo": "2023-2-Squad04",
    "contributor_count": 9,
    "contributors": [
      "DaniloCTM",
      "aqela-batata-alt",
      "github-project-automation[bot]",
      "Carlos-kadu",
      "patyhelenaa",
      "rayenealmeida",
      "RochaCarla",
      "Julio1099",
      "show-dawn"
    ],
    "potential_collaborations": 36,
    "actual_collaborations": 36,
    "collaboration_density": 1.0
  },
  {
    "repo": "2023-2-Squad05-TesouroMineiro",
    "contributor_count": 9,
    "contributors": [
      "Pedrin0030",
      "github-project-automation[bot]",
      "MuriloBDSR",
      "IderlanJ",
      "RochaCarla",
      "jheniferib",
      "claudiohsc",
      "EliasOliver21",
      "VictorGCOSTA"
    ],
    "potential_collaborations": 36,
    "actual_collaborations": 36,
    "collaboration_density": 1.0
  },
  {
    "repo": "2024-1-Squad02-CulturaTransparente",
    "contributor_count": 9,
    "contributors": [
      "mateuscavati",
      "vercel[bot]",
      "RochaCarla",
      "Goizzz",
      "isacostaf",
      "sidts",
      "PhFariaa",
      "andre-maia51",
      "JoseViniciusQueiroz"
    ],
    "potential_collaborations": 36,
    "actual_collaborations": 36,
    "collaboration_density": 1.0
  },
  {
    "repo": "Squad09-UnBHUB",
    "contributor_count": 9,
    "contributors": [
      "antonioscarvalho",
      "luccameds",
      "RochaCarla",
      "CristianoMoraiss",
      "TulioCeleri",
      "anawcarol",
      "czargab18",
      "FelipeRibeirooo",
      "G0ndim"
    ],
    "potential_collaborations": 36,
    "actual_collaborations": 36,
    "collaboration_density": 1.0
  },
  {
    "repo": "2024-1-Squad-10",
    "contributor_count": 9,
    "contributors": [
      "romuloreisdev",
      "mat054",
      "github-project-automation[bot]",
      "rmatuda",
      "RochaCarla",
      "PedroLock",
      "davi-aguiar-vieira",
      "henriquecarv3",
      "alvezclari"
    ],
    "potential_collaborations": 36,
    "actual_collaborations": 36,
    "collaboration_density": 1.0
  },
  {
    "repo": "DFemObras",
    "contributor_count": 9,
    "contributors": [
      "actions-user",
      "github-actions[bot]",
      "CaioMelo25",
      "RochaCarla",
      "JuliaReis18",
      "Nathan-bs",
      "Cayoalencar",
      "marcoslbz",
      "JpRodrigues2"
    ],
    "potential_collaborations": 36,
    "actual_collaborations": 36,
    "collaboration_density": 1.0
  },
  {
    "repo": "2025.1-RelatoriosInteligentesBCB",
    "contributor_count": 9,
    "contributors": [
      "BGrangeiro",
      "Nenalia02",
      "Luiskr34",
      "RafaelWasconcelos",
      "RochaCarla",
      "annaaju",
      "gabriel-ggf",
      "JhuliaCristina",
      "HenriqueFontenelle"
    ],
    "potential_collaborations": 36,
    "actual_collaborations": 36,
    "collaboration_density": 1.0
  },
  {
    "repo": "2025_1-Jakebot",
    "contributor_count": 9,
    "contributors": [
      "github-project-automation[bot]",
      "elopesm",
      "ArturGuanaes",
      "RochaCarla",
      "oicruc",
      "arturalvesfn",
      "EduardoRibeiroXavier",
      "LucasItacaramby",
      "auslogyc"
    ],
    "potential_collaborations": 36,
    "actual_collaborations": 36,
    "collaboration_density": 1.0
  },
  {
    "repo": "Projeto-P.I.T.E.R",
    "contributor_count": 9,
    "contributors": [
      "IsaLL24",
      "ananunesv",
      "Fofodoido",
      "Blazemorales",
      "RochaCarla",
      "PedroAraujo004",
      "GiuliaPaulucci",
      "Pirata2040",
      "PedroRSR"
    ],
    "potential_collaborations": 36,
    "actual_collaborations": 36,
    "collaboration_density": 1.0
  },
  {
    "repo": "2023-2-Squad09-Gotinha",
    "contributor_count": 8,
    "contributors": [
      "github-project-automation[bot]",
      "DudaV228",
      "RochaCarla",
      "LuizGust4vo",
      "yanzin00",
      "paulomh",
      "Mxrcio",
      "joao-artl"
    ],
    "potential_collaborations": 28,
    "actual_collaborations": 28,
    "collaboration_density": 1.0
  },
  {
    "repo": "2023-2-Squad10",
    "contributor_count": 8,
    "contributors": [
      "samuelalvess",
      "Sunamit",
      "LeoFacB",
      "RochaCarla",
      "xGabrielCv",
      "Filipe-002",
      "Guilermanoo",
      "Carlos42511"
    ],
    "potential_collaborations": 28,
    "actual_collaborations": 28,
    "collaboration_density": 1.0
  },
  {
    "repo": "2024-1-EducaMinas-frontend",
    "contributor_count": 8,
    "contributors": [
      "github-project-automation[bot]",
      "RochaCarla",
      "DanielFsR",
      "johan-rocha",
      "rafgpereira",
      "jlucasiqueira",
      "JoaoPedrooSS",
      "dudupaz"
    ],
    "potential_collaborations": 28,
    "actual_collaborations": 28,
    "collaboration_density": 1.0
  },
  {
    "repo": "2024-1-MinasDeCultura",
    "contributor_count": 8,
    "contributors": [
      "Gxaite",
      "manuvaladares",
      "Mateushqms",
      "WillxBernardo",
      "RochaCarla",
      "devMarcosVM",
      "rafaelcarvalhoj",
      "isaacbatista26"
    ],
    "potential_collaborations": 28,
    "actual_collaborations": 28,
    "collaboration_density": 1.0
  },
  {
    "repo": "Gastos-DF-Squad12",
    "contributor_count": 8,
    "contributors": [
      "victorcamaraa",
      "Dodeglinhass",
      "DanNunes777",
      "Ninja-Haiyai",
      "RochaCarla",
      "Vini47",
      "g4abr3la",
      "FelipeFreire-gf"
    ],
    "potential_collaborations": 28,
    "actual_collaborations": 28,
    "collaboration_density": 1.0
  },
  {
    "repo": "2024-2-Lumina",
    "contributor_count": 8,
    "contributors": [
      "arthurfernandesj",
      "luizh-gsoares",
      "github-project-automation[bot]",
      "felixlaryssa",
      "RochaCarla",
      "CaioPacheco",
      "LeticiaMonteiroo",
      "GabrielSPinto"
    ],
    "potential_collaborations": 28,
    "actual_collaborations": 28,
    "collaboration_density": 1.0
  },
  {
    "repo": "2024-2-Datazonia",
    "contributor_count": 8,
    "contributors": [
      "diego-card",
      "GuilhermeOliveira1327",
      "RochaCarla",
      "fdiogo1",
      "GuilhermeDavila",
      "bigkaio",
      "devwallyson",
      "renanpariiz"
    ],
    "potential_collaborations": 28,
    "actual_collaborations": 28,
    "collaboration_density": 1.0
  },
  {
    "repo": "Gastos-DF-2024-02",
    "contributor_count": 8,
    "contributors": [
      "actions-user",
      "BrzGab",
      "ArtyMend07",
      "JuliaGabP",
      "johnaopedro",
      "lucasarruda9",
      "RochaCarla",
      "Nibaacriba"
    ],
    "potential_collaborations": 28,
    "actual_collaborations": 28,
    "collaboration_density": 1.0
  },
  {
    "repo": "2025-1-Eletta",
    "contributor_count": 8,
    "contributors": [
      "enzo-fb",
      "github-project-automation[bot]",
      "rsribeiro1",
      "GiovanniMateus",
      "AndreLivio",
      "daviaraujobr",
      "RochaCarla",
      "LiviaYasmin"
    ],
    "potential_collaborations": 28,
    "actual_collaborations": 28,
    "collaboration_density": 1.0
  },
  {
    "repo": "2025-1-RelatAI",
    "contributor_count": 8,
    "contributors": [
      "KauaVL",
      "jv-ibiapina",
      "arthurhvieira1",
      "github-project-automation[bot]",
      "RochaCarla",
      "falaneh",
      "luabrantess",
      "pedrorocharfl"
    ],
    "potential_collaborations": 28,
    "actual_collaborations": 28,
    "collaboration_density": 1.0
  },
  {
    "repo": "2025-2-Eh_Fake",
    "contributor_count": 8,
    "contributors": [
      "github-project-automation[bot]",
      "Zaclonic",
      "RochaCarla",
      "Romm-0",
      "Davi-UnB",
      "Dandicalira",
      "Bryan70897",
      "Mateus0xC"
    ],
    "potential_collaborations": 28,
    "actual_collaborations": 28,
    "collaboration_density": 1.0
  },
  {
    "repo": "2025-2-Integralizei_UnB",
    "contributor_count": 8,
    "contributors": [
      "gpaulovit",
      "AnnaBeatrizAraujo",
      "carolinabecker",
      "GUGOFO",
      "RochaCarla",
      "menali17",
      "dependabot[bot]",
      "iicaroll"
    ],
    "potential_collaborations": 28,
    "actual_collaborations": 28,
    "collaboration_density": 1.0
  },
  {
    "repo": "2025-2-OncoMap",
    "contributor_count": 8,
    "contributors": [
      "Flyxs",
      "Alexandroni07",
      "RochaCarla",
      "ArturFGaldino",
      "Luizz97",
      "dependabot[bot]",
      "joaoPedro-201",
      "Gotc2607"
    ],
    "potential_collaborations": 28,
    "actual_collaborations": 28,
    "collaboration_density": 1.0
  },
  {
    "repo": "2025-2-InfoSchool",
    "contributor_count": 8,
    "contributors": [
      "LeonardoLopesJr",
      "DaviUrsulino",
      "Fabiovieira05",
      "PedroGomes-phgr",
      "macedoPedro20",
      "joaoleless",
      "RochaCarla",
      "ArturFGaldino"
    ],
    "potential_collaborations": 28,
    "actual_collaborations": 28,
    "collaboration_density": 1.0
  },
  {
    "repo": "2025-2-Mural-UnB",
    "contributor_count": 8,
    "contributors": [
      "github-actions[bot]",
      "luanludry",
      "apptrx",
      "RochaCarla",
      "MariaClara-Canuto",
      "Karmantinedev",
      "TiagoSBittencourt",
      "Lucasft16"
    ],
    "potential_collaborations": 28,
    "actual_collaborations": 28,
    "collaboration_density": 1.0
  },
  {
    "repo": "2025-2-Lumina",
    "contributor_count": 8,
    "contributors": [
      "nathanpromao",
      "Atila05",
      "github-project-automation[bot]",
      "ArthurLuizUnB",
      "CeciliaCunha",
      "RochaCarla",
      "Joao-PFG",
      "TiagoUNB"
    ],
    "potential_collaborations": 28,
    "actual_collaborations": 28,
    "collaboration_density": 1.0
  },
  {
    "repo": "2025-2-Synapse",
    "contributor_count": 8,
    "contributors": [
      "g-srodrigues",
      "ArthurDevWorks",
      "github-project-automation[bot]",
      "ItaloSamP",
      "Sismene7",
      "RochaCarla",
      "Dgprogramas",
      "gccintra"
    ],
    "potential_collaborations": 28,
    "actual_collaborations": 28,
    "collaboration_density": 1.0
  },
  {
    "repo": "2023-2-Squad01",
    "contributor_count": 7,
    "contributors": [
      "caua08",
      "Tutzs",
      "RochaCarla",
      "femathrl",
      "ailujana",
      "Oleari19",
      "julia-fortunato"
    ],
    "potential_collaborations": 21,
    "actual_collaborations": 21,
    "collaboration_density": 1.0
  },
  {
    "repo": "2023-2-Squad07",
    "contributor_count": 7,
    "contributors": [
      "joseandre25",
      "yuri221022210",
      "RochaCarla",
      "juliatakaki",
      "RafaBonach",
      "samarawwleticia",
      "gio221"
    ],
    "potential_collaborations": 21,
    "actual_collaborations": 21,
    "collaboration_density": 1.0
  },
  {
    "repo": "2024-1-forUnB",
    "contributor_count": 7,
    "contributors": [
      "Davi-KLevy",
      "RochaCarla",
      "pLopess",
      "BrunoBReis",
      "VHbernardes",
      "AlexandreLJr",
      "manu-sgc"
    ],
    "potential_collaborations": 21,
    "actual_collaborations": 21,
    "collaboration_density": 1.0
  },
  {
    "repo": "2024-1-squad04",
    "contributor_count": 7,
    "contributors": [
      "leticiatmartins",
      "vitor-hoffmann",
      "RochaCarla",
      "unb-mds",
      "ana-pfeilsticker",
      "Atyrson",
      "mtsmgn0"
    ],
    "potential_collaborations": 21,
    "actual_collaborations": 21,
    "collaboration_density": 1.0
  },
  {
    "repo": "2024-1-Squad08",
    "contributor_count": 7,
    "contributors": [
      "RA-Salles",
      "Brunocrzz",
      "Renurin",
      "pedroeverton217",
      "RochaCarla",
      "unb-mds",
      "Discicle"
    ],
    "potential_collaborations": 21,
    "actual_collaborations": 21,
    "collaboration_density": 1.0
  },
  {
    "repo": "2024-1-EducaMinas-backend",
    "contributor_count": 7,
    "contributors": [
      "github-project-automation[bot]",
      "RochaCarla",
      "johan-rocha",
      "DanielFsR",
      "rafgpereira",
      "JoaoPedrooSS",
      "dudupaz"
    ],
    "potential_collaborations": 21,
    "actual_collaborations": 21,
    "collaboration_density": 1.0
  },
  {
    "repo": "2024-2-Squad01",
    "contributor_count": 7,
    "contributors": [
      "pyramidsf",
      "luluaroeira",
      "RochaCarla",
      "joaofmoreiraa",
      "mclarasena",
      "SAnjos3",
      "MylenaTrindade"
    ],
    "potential_collaborations": 21,
    "actual_collaborations": 21,
    "collaboration_density": 1.0
  },
  {
    "repo": "2024-2-Urbanize",
    "contributor_count": 7,
    "contributors": [
      "angelicaccampos",
      "gabriel-lima258",
      "Fernandavazgit1",
      "Bessazs",
      "leozinlima",
      "RochaCarla",
      "MateuSansete"
    ],
    "potential_collaborations": 21,
    "actual_collaborations": 21,
    "collaboration_density": 1.0
  },
  {
    "repo": "2024-2-Agio",
    "contributor_count": 7,
    "contributors": [
      "eduardodpms",
      "EnzoEmir",
      "RochaCarla",
      "MM4k",
      "caio-venancio",
      "VictorPontual",
      "JMPNascimento"
    ],
    "potential_collaborations": 21,
    "actual_collaborations": 21,
    "collaboration_density": 1.0
  },
  {
    "repo": "MDS-MonitoraBSB",
    "contributor_count": 7,
    "contributors": [
      "paulocerqr",
      "DanNunes777",
      "erickaalves",
      "gustavolima973",
      "RochaCarla",
      "Beatriz-ge",
      "Mach1r0"
    ],
    "potential_collaborations": 21,
    "actual_collaborations": 21,
    "collaboration_density": 1.0
  },
  {
    "repo": "2024-2-ChamaControl",
    "contributor_count": 7,
    "contributors": [
      "Diaxiz",
      "Arturhk05",
      "leohssjr",
      "RochaCarla",
      "Edumorais08",
      "Guga301104",
      "fbressa"
    ],
    "potential_collaborations": 21,
    "actual_collaborations": 21,
    "collaboration_density": 1.0
  },
  {
    "repo": "2024-2-SuaFinanca",
    "contributor_count": 7,
    "contributors": [
      "kalebmacedo",
      "LucasMF1",
      "cibelinda",
      "RochaCarla",
      "samuelncaetano",
      "PedroAraujo004",
      "LucasAlves71"
    ],
    "potential_collaborations": 21,
    "actual_collaborations": 21,
    "collaboration_density": 1.0
  },
  {
    "repo": "2025-2-Portal-dos-Professores",
    "contributor_count": 7,
    "contributors": [
      "Paulosrsr",
      "brunodantas9",
      "KaioAmouryUnB",
      "RochaCarla",
      "caiolacerdamt",
      "ianpedersoli",
      "Ascartezin"
    ],
    "potential_collaborations": 21,
    "actual_collaborations": 21,
    "collaboration_density": 1.0
  },
  {
    "repo": "2025-2-SeLiga",
    "contributor_count": 7,
    "contributors": [
      "arthurvbl",
      "lopes061",
      "MarcusVRezende",
      "RochaCarla",
      "ErickRyan-pimba",
      "amandalimaps",
      "GustavoEmmanuel-1"
    ],
    "potential_collaborations": 21,
    "actual_collaborations": 21,
    "collaboration_density": 1.0
  },
  {
    "repo": "2025-2-GuiaDev",
    "contributor_count": 7,
    "contributors": [
      "BGrangeiro",
      "RochaCarla",
      "JoaoGSantana10",
      "HugoFreitass",
      "PedroGTG",
      "Phill-Chill",
      "filipeBG-07"
    ],
    "potential_collaborations": 21,
    "actual_collaborations": 21,
    "collaboration_density": 1.0
  },
  {
    "repo": "Mds-ArenaPesadelo",
    "contributor_count": 6,
    "contributors": [
      "RochaCarla",
      "drykette",
      "PauloFilho2",
      "BrunoOLiveirax",
      "PedroALuciano",
      "zlimaz"
    ],
    "potential_collaborations": 15,
    "actual_collaborations": 15,
    "collaboration_density": 1.0
  },
  {
    "repo": "2025-2-Squad12",
    "contributor_count": 6,
    "contributors": [
      "arthursouto09",
      "Jp-te",
      "TsukiRaiito",
      "RochaCarla",
      "SemC0ndicao",
      "Antedeguemon21"
    ],
    "potential_collaborations": 15,
    "actual_collaborations": 15,
    "collaboration_density": 1.0
  },
  {
    "repo": "squad03-r2",
    "contributor_count": 5,
    "contributors": [
      "DiegoSousaLeite",
      "RochaCarla",
      "Paxxaglia",
      "M4RINH0",
      "joycedio"
    ],
    "potential_collaborations": 10,
    "actual_collaborations": 10,
    "collaboration_density": 1.0
  },
  {
    "repo": "2023.2_Licitaiba",
    "contributor_count": 5,
    "contributors": [
      "DaniloCTM",
      "aqela-batata-alt",
      "Carlos-kadu",
      "rayenealmeida",
      "RochaCarla"
    ],
    "potential_collaborations": 10,
    "actual_collaborations": 10,
    "collaboration_density": 1.0
  },
  {
    "repo": "2024-1-Gastos-DF-Doc-Squad12",
    "contributor_count": 5,
    "contributors": [
      "victorcamaraa",
      "DanNunes777",
      "Ninja-Haiyai",
      "RochaCarla",
      "Vini47"
    ],
    "potential_collaborations": 10,
    "actual_collaborations": 10,
    "collaboration_density": 1.0
  },
  {
    "repo": "2023.2-LicitaX",
    "contributor_count": 4,
    "contributors": [
      "juliatakaki",
      "RafaBonach",
      "joseandre25",
      "gio221"
    ],
    "potential_collaborations": 6,
    "actual_collaborations": 6,
    "collaboration_density": 1.0
  },
  {
    "repo": "portfolio-MDS",
    "contributor_count": 4,
    "contributors": [
      "marcoslbz",
      "Beatriz-ge",
      "JuliaGabP",
      "pedroeverton217"
    ],
    "potential_collaborations": 6,
    "actual_collaborations": 6,
    "collaboration_density": 1.0
  },
  {
    "repo": "2023.2_Gotinha",
    "contributor_count": 3,
    "contributors": [
      "joao-artl",
      "RochaCarla",
      "paulomh"
    ],
    "potential_collaborations": 3,
    "actual_collaborations": 3,
    "collaboration_density": 1.0
  },
  {
    "repo": "carlarocha",
    "contributor_count": 2,
    "contributors": [
      "arthurbdiniz",
      "devto-bot"
    ],
    "potential_collaborations": 1,
    "actual_collaborations": 1,
    "collaboration_density": 1.0
  },
  {
    "repo": "teste",
    "contributor_count": 1,
    "contributors": [
      "RochaCarla"
    ],
    "potential_collaborations": 0,
    "actual_collaborations": 0,
    "collaboration_density": 0
  },
  {
    "repo": "exemplogitpage",
    "contributor_count": 1,
    "contributors": [
      "RochaCarla"
    ],
    "potential_collaborations": 0,
    "actual_collaborations": 0,
    "collaboration_density": 0
  },
  {
    "repo": ".github",
    "contributor_count": 1,
    "contributors": [
      "RochaCarla"
    ],
    "potential_collaborations": 0,
    "actual_collaborations": 0,
    "collaboration_density": 0
  }
]