[
  {
    "_metadata": {
      "extracted_at": "2025-11-25T18:57:01.358541",
      "file_path": "data/gold/timeline_last_7_days.json",
      "record_count": 7
    }
  },
  {
    "date": "2025-11-11",
    "total_events": 215,
    "issues_created": 10,
    "issues_closed": 11,
    "prs_created": 10,
    "prs_closed": 7,
    "commits": 20,
    "comments": 0,
    "unique_users": 38,
    "unique_repos": 10,
    "authors": [
      {
        "name": "filipeBG-07",
        "commits": 0,
        "issues_created": 0,
        "issues_closed": 1,
        "prs_created": 0,
        "prs_closed": 1,
        "comments": 0,
        "repositories": [
          "2025-2-GuiaDev"
        ]
      },
      {
        "name": "HugoFreitass",
        "commits": 0,
        "issues_created": 1,
        "issues_closed": 1,
        "prs_created": 1,
        "prs_closed": 0,
        "comments": 0,
        "repositories": [
          "2025-2-GuiaDev",
          "Avalia"
        ]
      },
      {
        "name": "BGrangeiro",
        "commits": 0,
        "issues_created": 0,
        "issues_closed": 1,
        "prs_created": 1,
        "prs_closed": 0,
        "comments": 0,
        "repositories": [
          "2025-2-GuiaDev",
          "2025.1-RelatoriosInteligentesBCB"
        ]
      },
      {
        "name": "PedroGTG",
        "commits": 0,
        "issues_created": 1,
        "issues_closed": 1,
        "prs_created": 0,
        "prs_closed": 0,
        "comments": 0,
        "repositories": [
          "2025-2-GuiaDev"
        ]
      },
      {
        "name": "Phill-Chill",
        "commits": 0,
        "issues_created": 0,
        "issues_closed": 1,
        "prs_created": 0,
        "prs_closed": 0,
        "comments": 0,
        "repositories": [
          "2025-2-GuiaDev"
        ]
      },
      {
        "name": "TiagoUNB",
        "commits": 0,
        "issues_created": 0,
        "issues_closed": 0,
        "prs_created": 1,
        "prs_closed": 1,
        "comments": 0,
        "repositories": [
          "2025-2-Lumina"
        ]
      },
      {
        "name": "GitHub Actions Bot",
        "commits": 1,
        "issues_created": 0,
        "issues_closed": 0,
        "prs_created": 0,
        "prs_closed": 0,
        "comments": 0,
        "repositories": [
          "2025-2-Mural-UnB",
          "DFemObras",
          "DFemObras-2025.1"
        ]
      },
      {
        "name": "CeciliaCunha",
        "commits": 0,
        "issues_created": 1,
        "issues_closed": 0,
        "prs_created": 1,
        "prs_closed": 2,
        "comments": 0,
        "repositories": [
          "2025-2-Lumina"
        ]
      },
      {
        "name": "Joao-PFG",
        "commits": 0,
        "issues_created": 1,
        "issues_closed": 1,
        "prs_created": 1,
        "prs_closed": 0,
        "comments": 0,
        "repositories": [
          "2025-2-Lumina"
        ]
      },
      {
        "name": "nathanpromao",
        "commits": 0,
        "issues_created": 0,
        "issues_closed": 0,
        "prs_created": 1,
        "prs_closed": 0,
        "comments": 0,
        "repositories": [
          "2025-2-Lumina"
        ]
      },
      {
        "name": "Github Actions",
        "commits": 1,
        "issues_created": 0,
        "issues_closed": 0,
        "prs_created": 0,
        "prs_closed": 0,
        "comments": 0,
        "repositories": [
          "2023-2-Squad04",
          "DFemObras",
          "DFemObras-2025.1",
          "LicitaBSB-24.1"
        ]
      },
      {
        "name": "github-actions[bot]",
        "commits": 2,
        "issues_created": 0,
        "issues_closed": 0,
        "prs_created": 0,
        "prs_closed": 0,
        "comments": 0,
        "repositories": [
          "2024-2-SuaFinanca",
          "2025-2-Eh_Fake",
          "2025-2-Squad-01",
          "DFemObras-2025.1",
          "FixIt"
        ]
      },
      {
        "name": "arthurvbl",
        "commits": 0,
        "issues_created": 2,
        "issues_closed": 2,
        "prs_created": 1,
        "prs_closed": 0,
        "comments": 0,
        "repositories": [
          "2025-2-SeLiga"
        ]
      },
      {
        "name": "Ana",
        "commits": 3,
        "issues_created": 0,
        "issues_closed": 0,
        "prs_created": 0,
        "prs_closed": 0,
        "comments": 0,
        "repositories": [
          "2025-2-Integralizei_UnB"
        ]
      },
      {
        "name": "luanludry",
        "commits": 0,
        "issues_created": 0,
        "issues_closed": 1,
        "prs_created": 0,
        "prs_closed": 0,
        "comments": 0,
        "repositories": [
          "2025-2-Mural-UnB"
        ]
      },
      {
        "name": "Paulo Sérgio",
        "commits": 2,
        "issues_created": 0,
        "issues_closed": 0,
        "prs_created": 0,
        "prs_closed": 0,
        "comments": 0,
        "repositories": [
          "2025-2-Portal-dos-Professores"
        ]
      },
      {
        "name": "HeitorM50",
        "commits": 0,
        "issues_created": 1,
        "issues_closed": 0,
        "prs_created": 0,
        "prs_closed": 0,
        "comments": 0,
        "repositories": [
          "2025-2-Squad-01"
        ]
      },
      {
        "name": "iicaroll",
        "commits": 0,
        "issues_created": 0,
        "issues_closed": 0,
        "prs_created": 1,
        "prs_closed": 1,
        "comments": 0,
        "repositories": [
          "2025-2-Integralizei_UnB"
        ]
      },
      {
        "name": "Paulosrsr",
        "commits": 0,
        "issues_created": 1,
        "issues_closed": 0,
        "prs_created": 1,
        "prs_closed": 1,
        "comments": 0,
        "repositories": [
          "2025-2-Portal-dos-Professores"
        ]
      },
      {
        "name": "Ascartezin",
        "commits": 0,
        "issues_created": 0,
        "issues_closed": 1,
        "prs_created": 0,
        "prs_closed": 0,
        "comments": 0,
        "repositories": [
          "2025-2-Portal-dos-Professores"
        ]
      },
      {
        "name": "LucasFT",
        "commits": 5,
        "issues_created": 0,
        "issues_closed": 0,
        "prs_created": 0,
        "prs_closed": 0,
        "comments": 0,
        "repositories": [
          "2025-2-Mural-UnB"
        ]
      },
      {
        "name": "caiolacerdamt",
        "commits": 0,
        "issues_created": 2,
        "issues_closed": 0,
        "prs_created": 0,
        "prs_closed": 0,
        "comments": 0,
        "repositories": [
          "2025-2-Portal-dos-Professores"
        ]
      },
      {
        "name": "Lucas Fujimoto Tokunaga",
        "commits": 1,
        "issues_created": 0,
        "issues_closed": 0,
        "prs_created": 0,
        "prs_closed": 0,
        "comments": 0,
        "repositories": [
          "2025-2-Mural-UnB"
        ]
      },
      {
        "name": "Enzo Menali",
        "commits": 1,
        "issues_created": 0,
        "issues_closed": 0,
        "prs_created": 0,
        "prs_closed": 0,
        "comments": 0,
        "repositories": [
          "2025-2-Integralizei_UnB"
        ]
      },
      {
        "name": "Bruno Henryque Grangeiro",
        "commits": 2,
        "issues_created": 0,
        "issues_closed": 0,
        "prs_created": 0,
        "prs_closed": 0,
        "comments": 0,
        "repositories": [
          "2025-2-GuiaDev"
        ]
      },
      {
        "name": "Lucasft16",
        "commits": 1,
        "issues_created": 0,
        "issues_closed": 1,
        "prs_created": 1,
        "prs_closed": 1,
        "comments": 0,
        "repositories": [
          "2025-2-Mural-UnB"
        ]
      },
      {
        "name": "Davi Severiano",
        "commits": 1,
        "issues_created": 0,
        "issues_closed": 0,
        "prs_created": 0,
        "prs_closed": 0,
        "comments": 0,
        "repositories": [
          "2025-2-Eh_Fake"
        ]
      }
    ]
  },
  {
    "date": "2025-11-12",
    "total_events": 190,
    "issues_created": 11,
    "issues_closed": 5,
    "prs_created": 10,
    "prs_closed": 8,
    "commits": 31,
    "comments": 0,
    "unique_users": 33,
    "unique_repos": 13,
    "authors": [
      {
        "name": "BGrangeiro",
        "commits": 0,
        "issues_created": 0,
        "issues_closed": 0,
        "prs_created": 0,
        "prs_closed": 1,
        "comments": 0,
        "repositories": [
          "2025-2-GuiaDev",
          "2025.1-RelatoriosInteligentesBCB"
        ]
      },
      {
        "name": "GitHub Actions Bot",
        "commits": 1,
        "issues_created": 0,
        "issues_closed": 0,
        "prs_created": 0,
        "prs_closed": 0,
        "comments": 0,
        "repositories": [
          "2025-2-Mural-UnB",
          "DFemObras",
          "DFemObras-2025.1"
        ]
      },
      {
        "name": "Davi-UnB",
        "commits": 0,
        "issues_created": 1,
        "issues_closed": 1,
        "prs_created": 0,
        "prs_closed": 0,
        "comments": 0,
        "repositories": [
          "2025-2-Eh_Fake"
        ]
      },
      {
        "name": "iicaroll",
        "commits": 0,
        "issues_created": 0,
        "issues_closed": 0,
        "prs_created": 1,
        "prs_closed": 0,
        "comments": 0,
        "repositories": [
          "2025-2-Integralizei_UnB"
        ]
      },
      {
        "name": "nathanpromao",
        "commits": 1,
        "issues_created": 2,
        "issues_closed": 0,
        "prs_created": 0,
        "prs_closed": 0,
        "comments": 0,
        "repositories": [
          "2025-2-Lumina"
        ]
      },
      {
        "name": "pedrogrocha13",
        "commits": 1,
        "issues_created": 0,
        "issues_closed": 1,
        "prs_created": 1,
        "prs_closed": 1,
        "comments": 0,
        "repositories": [
          "2025-2-Squad-01"
        ]
      },
      {
        "name": "cadumotta",
        "commits": 1,
        "issues_created": 1,
        "issues_closed": 0,
        "prs_created": 1,
        "prs_closed": 0,
        "comments": 0,
        "repositories": [
          "2025-2-Squad-01"
        ]
      },
      {
        "name": "Github Actions",
        "commits": 3,
        "issues_created": 0,
        "issues_closed": 0,
        "prs_created": 0,
        "prs_closed": 0,
        "comments": 0,
        "repositories": [
          "2023-2-Squad04",
          "DFemObras",
          "DFemObras-2025.1",
          "LicitaBSB-24.1"
        ]
      },
      {
        "name": "github-actions[bot]",
        "commits": 4,
        "issues_created": 0,
        "issues_closed": 0,
        "prs_created": 0,
        "prs_closed": 0,
        "comments": 0,
        "repositories": [
          "2024-2-SuaFinanca",
          "2025-2-Eh_Fake",
          "2025-2-Squad-01",
          "DFemObras-2025.1",
          "FixIt"
        ]
      },
      {
        "name": "TiagoUNB",
        "commits": 2,
        "issues_created": 2,
        "issues_closed": 0,
        "prs_created": 1,
        "prs_closed": 0,
        "comments": 0,
        "repositories": [
          "2025-2-Lumina"
        ]
      },
      {
        "name": "Luizz97",
        "commits": 0,
        "issues_created": 0,
        "issues_closed": 1,
        "prs_created": 0,
        "prs_closed": 0,
        "comments": 0,
        "repositories": [
          "2025-2-OncoMap"
        ]
      },
      {
        "name": "Blazemorales",
        "commits": 0,
        "issues_created": 0,
        "issues_closed": 0,
        "prs_created": 2,
        "prs_closed": 2,
        "comments": 0,
        "repositories": [
          "Projeto-P.I.T.E.R"
        ]
      },
      {
        "name": "GiuliaPaulucci",
        "commits": 0,
        "issues_created": 0,
        "issues_closed": 0,
        "prs_created": 0,
        "prs_closed": 1,
        "comments": 0,
        "repositories": [
          "Projeto-P.I.T.E.R"
        ]
      },
      {
        "name": "Pirata2040",
        "commits": 0,
        "issues_created": 0,
        "issues_closed": 2,
        "prs_created": 0,
        "prs_closed": 0,
        "comments": 0,
        "repositories": [
          "Projeto-P.I.T.E.R"
        ]
      },
      {
        "name": "Copilot",
        "commits": 0,
        "issues_created": 0,
        "issues_closed": 0,
        "prs_created": 1,
        "prs_closed": 1,
        "comments": 0,
        "repositories": [
          "2025-2-Squad-01",
          "DFemObras-2025.1"
        ]
      },
      {
        "name": "Ascartezin",
        "commits": 0,
        "issues_created": 1,
        "issues_closed": 0,
        "prs_created": 0,
        "prs_closed": 0,
        "comments": 0,
        "repositories": [
          "2025-2-Portal-dos-Professores"
        ]
      },
      {
        "name": "guxvr",
        "commits": 0,
        "issues_created": 1,
        "issues_closed": 0,
        "prs_created": 1,
        "prs_closed": 0,
        "comments": 0,
        "repositories": [
          "2025-2-Squad-01",
          "Avalia"
        ]
      },
      {
        "name": "Paulo Sérgio",
        "commits": 2,
        "issues_created": 0,
        "issues_closed": 0,
        "prs_created": 0,
        "prs_closed": 0,
        "comments": 0,
        "repositories": [
          "2025-2-Portal-dos-Professores"
        ]
      },
      {
        "name": "caiolacerdamt",
        "commits": 8,
        "issues_created": 0,
        "issues_closed": 0,
        "prs_created": 1,
        "prs_closed": 1,
        "comments": 0,
        "repositories": [
          "2025-2-Portal-dos-Professores"
        ]
      },
      {
        "name": "Caio Lacerda",
        "commits": 2,
        "issues_created": 0,
        "issues_closed": 0,
        "prs_created": 0,
        "prs_closed": 0,
        "comments": 0,
        "repositories": [
          "2025-2-Portal-dos-Professores"
        ]
      },
      {
        "name": "ErickRyan-pimba",
        "commits": 1,
        "issues_created": 0,
        "issues_closed": 0,
        "prs_created": 0,
        "prs_closed": 0,
        "comments": 0,
        "repositories": [
          "2025-2-SeLiga"
        ]
      },
      {
        "name": "Atila05",
        "commits": 0,
        "issues_created": 2,
        "issues_closed": 0,
        "prs_created": 0,
        "prs_closed": 0,
        "comments": 0,
        "repositories": [
          "2025-2-Lumina"
        ]
      },
      {
        "name": "Paulosrsr",
        "commits": 0,
        "issues_created": 0,
        "issues_closed": 0,
        "prs_created": 1,
        "prs_closed": 0,
        "comments": 0,
        "repositories": [
          "2025-2-Portal-dos-Professores"
        ]
      },
      {
        "name": "João Guilherme Santana de Oliveira",
        "commits": 2,
        "issues_created": 0,
        "issues_closed": 0,
        "prs_created": 0,
        "prs_closed": 0,
        "comments": 0,
        "repositories": [
          "2025-2-GuiaDev"
        ]
      },
      {
        "name": "arthurvbl",
        "commits": 0,
        "issues_created": 1,
        "issues_closed": 0,
        "prs_created": 0,
        "prs_closed": 0,
        "comments": 0,
        "repositories": [
          "2025-2-SeLiga"
        ]
      },
      {
        "name": "Joao-PFG",
        "commits": 0,
        "issues_created": 0,
        "issues_closed": 0,
        "prs_created": 0,
        "prs_closed": 1,
        "comments": 0,
        "repositories": [
          "2025-2-Lumina"
        ]
      },
      {
        "name": "Ana",
        "commits": 2,
        "issues_created": 0,
        "issues_closed": 0,
        "prs_created": 0,
        "prs_closed": 0,
        "comments": 0,
        "repositories": [
          "2025-2-Integralizei_UnB"
        ]
      },
      {
        "name": "Ana Caroline",
        "commits": 1,
        "issues_created": 0,
        "issues_closed": 0,
        "prs_created": 0,
        "prs_closed": 0,
        "comments": 0,
        "repositories": [
          "2025-2-Integralizei_UnB"
        ]
      }
    ]
  },
  {
    "date": "2025-11-13",
    "total_events": 127,
    "issues_created": 9,
    "issues_closed": 13,
    "prs_created": 4,
    "prs_closed": 10,
    "commits": 20,
    "comments": 0,
    "unique_users": 28,
    "unique_repos": 11,
    "authors": [
      {
        "name": "Paulo Sérgio",
        "commits": 1,
        "issues_created": 0,
        "issues_closed": 0,
        "prs_created": 0,
        "prs_closed": 0,
        "comments": 0,
        "repositories": [
          "2025-2-Portal-dos-Professores"
        ]
      },
      {
        "name": "iicaroll",
        "commits": 0,
        "issues_created": 0,
        "issues_closed": 0,
        "prs_created": 2,
        "prs_closed": 2,
        "comments": 0,
        "repositories": [
          "2025-2-Integralizei_UnB"
        ]
      },
      {
        "name": "Phill",
        "commits": 1,
        "issues_created": 0,
        "issues_closed": 0,
        "prs_created": 0,
        "prs_closed": 0,
        "comments": 0,
        "repositories": [
          "2025-2-GuiaDev"
        ]
      },
      {
        "name": "caiolacerdamt",
        "commits": 0,
        "issues_created": 0,
        "issues_closed": 0,
        "prs_created": 1,
        "prs_closed": 1,
        "comments": 0,
        "repositories": [
          "2025-2-Portal-dos-Professores"
        ]
      },
      {
        "name": "cadumotta",
        "commits": 1,
        "issues_created": 0,
        "issues_closed": 1,
        "prs_created": 0,
        "prs_closed": 1,
        "comments": 0,
        "repositories": [
          "2025-2-Squad-01"
        ]
      },
      {
        "name": "Paulosrsr",
        "commits": 0,
        "issues_created": 0,
        "issues_closed": 0,
        "prs_created": 0,
        "prs_closed": 2,
        "comments": 0,
        "repositories": [
          "2025-2-Portal-dos-Professores"
        ]
      },
      {
        "name": "nathanpromao",
        "commits": 0,
        "issues_created": 0,
        "issues_closed": 0,
        "prs_created": 0,
        "prs_closed": 1,
        "comments": 0,
        "repositories": [
          "2025-2-Lumina"
        ]
      },
      {
        "name": "HugoFreitass",
        "commits": 0,
        "issues_created": 0,
        "issues_closed": 1,
        "prs_created": 0,
        "prs_closed": 1,
        "comments": 0,
        "repositories": [
          "2025-2-GuiaDev",
          "Avalia"
        ]
      },
      {
        "name": "Github Actions",
        "commits": 3,
        "issues_created": 0,
        "issues_closed": 0,
        "prs_created": 0,
        "prs_closed": 0,
        "comments": 0,
        "repositories": [
          "2023-2-Squad04",
          "DFemObras",
          "DFemObras-2025.1",
          "LicitaBSB-24.1"
        ]
      },
      {
        "name": "github-actions[bot]",
        "commits": 4,
        "issues_created": 0,
        "issues_closed": 0,
        "prs_created": 0,
        "prs_closed": 0,
        "comments": 0,
        "repositories": [
          "2024-2-SuaFinanca",
          "2025-2-Eh_Fake",
          "2025-2-Squad-01",
          "DFemObras-2025.1",
          "FixIt"
        ]
      },
      {
        "name": "ErickRyan-pimba",
        "commits": 5,
        "issues_created": 0,
        "issues_closed": 0,
        "prs_created": 0,
        "prs_closed": 0,
        "comments": 0,
        "repositories": [
          "2025-2-SeLiga"
        ]
      },
      {
        "name": "BGrangeiro",
        "commits": 0,
        "issues_created": 0,
        "issues_closed": 1,
        "prs_created": 0,
        "prs_closed": 0,
        "comments": 0,
        "repositories": [
          "2025-2-GuiaDev",
          "2025.1-RelatoriosInteligentesBCB"
        ]
      },
      {
        "name": "Dgprogramas",
        "commits": 0,
        "issues_created": 2,
        "issues_closed": 0,
        "prs_created": 0,
        "prs_closed": 0,
        "comments": 0,
        "repositories": [
          "2025-2-Synapse"
        ]
      },
      {
        "name": "guxvr",
        "commits": 0,
        "issues_created": 0,
        "issues_closed": 0,
        "prs_created": 0,
        "prs_closed": 1,
        "comments": 0,
        "repositories": [
          "2025-2-Squad-01",
          "Avalia"
        ]
      },
      {
        "name": "pedrogrocha13",
        "commits": 1,
        "issues_created": 0,
        "issues_closed": 0,
        "prs_created": 0,
        "prs_closed": 0,
        "comments": 0,
        "repositories": [
          "2025-2-Squad-01"
        ]
      },
      {
        "name": "Luizz97",
        "commits": 1,
        "issues_created": 0,
        "issues_closed": 0,
        "prs_created": 0,
        "prs_closed": 0,
        "comments": 0,
        "repositories": [
          "2025-2-OncoMap"
        ]
      },
      {
        "name": "Arthur Laterza",
        "commits": 1,
        "issues_created": 0,
        "issues_closed": 0,
        "prs_created": 0,
        "prs_closed": 0,
        "comments": 0,
        "repositories": [
          "2025-2-SeLiga"
        ]
      },
      {
        "name": "pedruck",
        "commits": 0,
        "issues_created": 1,
        "issues_closed": 0,
        "prs_created": 1,
        "prs_closed": 0,
        "comments": 0,
        "repositories": [
          "2025-2-Squad-01",
          "Avalia"
        ]
      },
      {
        "name": "João Guilherme Santana de Oliveira",
        "commits": 1,
        "issues_created": 0,
        "issues_closed": 0,
        "prs_created": 0,
        "prs_closed": 0,
        "comments": 0,
        "repositories": [
          "2025-2-GuiaDev"
        ]
      },
      {
        "name": "Antedeguemon21",
        "commits": 0,
        "issues_created": 1,
        "issues_closed": 6,
        "prs_created": 0,
        "prs_closed": 0,
        "comments": 0,
        "repositories": [
          "2025-2-Squad12",
          "DFemObras-2025.1"
        ]
      },
      {
        "name": "TsukiRaiito",
        "commits": 0,
        "issues_created": 5,
        "issues_closed": 3,
        "prs_created": 0,
        "prs_closed": 0,
        "comments": 0,
        "repositories": [
          "2025-2-Squad12"
        ]
      },
      {
        "name": "arthursouto09",
        "commits": 0,
        "issues_created": 0,
        "issues_closed": 1,
        "prs_created": 0,
        "prs_closed": 0,
        "comments": 0,
        "repositories": [
          "2025-2-Squad12"
        ]
      },
      {
        "name": "arthurvbl",
        "commits": 0,
        "issues_created": 0,
        "issues_closed": 0,
        "prs_created": 0,
        "prs_closed": 1,
        "comments": 0,
        "repositories": [
          "2025-2-SeLiga"
        ]
      },
      {
        "name": "brunodantas9",
        "commits": 1,
        "issues_created": 0,
        "issues_closed": 0,
        "prs_created": 0,
        "prs_closed": 0,
        "comments": 0,
        "repositories": [
          "2025-2-Portal-dos-Professores",
          "Avalia"
        ]
      }
    ]
  },
  {
    "date": "2025-11-14",
    "total_events": 134,
    "issues_created": 7,
    "issues_closed": 0,
    "prs_created": 16,
    "prs_closed": 3,
    "commits": 25,
    "comments": 0,
    "unique_users": 32,
    "unique_repos": 10,
    "authors": [
      {
        "name": "brunodantas9",
        "commits": 9,
        "issues_created": 1,
        "issues_closed": 0,
        "prs_created": 4,
        "prs_closed": 3,
        "comments": 0,
        "repositories": [
          "2025-2-Portal-dos-Professores",
          "Avalia"
        ]
      },
      {
        "name": "GitHub Actions Bot",
        "commits": 1,
        "issues_created": 0,
        "issues_closed": 0,
        "prs_created": 0,
        "prs_closed": 0,
        "comments": 0,
        "repositories": [
          "2025-2-Mural-UnB",
          "DFemObras",
          "DFemObras-2025.1"
        ]
      },
      {
        "name": "JoaoGSantana10",
        "commits": 0,
        "issues_created": 1,
        "issues_closed": 0,
        "prs_created": 0,
        "prs_closed": 0,
        "comments": 0,
        "repositories": [
          "2025-2-GuiaDev"
        ]
      },
      {
        "name": "ItaloSamP",
        "commits": 0,
        "issues_created": 0,
        "issues_closed": 0,
        "prs_created": 1,
        "prs_closed": 0,
        "comments": 0,
        "repositories": [
          "2025-2-Synapse"
        ]
      },
      {
        "name": "Github Actions",
        "commits": 3,
        "issues_created": 0,
        "issues_closed": 0,
        "prs_created": 0,
        "prs_closed": 0,
        "comments": 0,
        "repositories": [
          "2023-2-Squad04",
          "DFemObras",
          "DFemObras-2025.1",
          "LicitaBSB-24.1"
        ]
      },
      {
        "name": "github-actions[bot]",
        "commits": 2,
        "issues_created": 0,
        "issues_closed": 0,
        "prs_created": 0,
        "prs_closed": 0,
        "comments": 0,
        "repositories": [
          "2024-2-SuaFinanca",
          "2025-2-Eh_Fake",
          "2025-2-Squad-01",
          "DFemObras-2025.1",
          "FixIt"
        ]
      },
      {
        "name": "Carla Rocha",
        "commits": 2,
        "issues_created": 0,
        "issues_closed": 0,
        "prs_created": 0,
        "prs_closed": 0,
        "comments": 0,
        "repositories": [
          ".github",
          "2023-2-JuizVirtual",
          "2023-2-Squad01",
          "2023-2-Squad02-Desmatazonia",
          "2023-2-Squad03-LicitAL",
          "2023-2-Squad04",
          "2023-2-Squad05-TesouroMineiro",
          "2023-2-Squad07",
          "2023-2-Squad09-Gotinha",
          "2023-2-Squad10",
          "2023-2-SuaGradeUnB",
          "2023.2_DeOlhoRS",
          "2023.2_Gotinha",
          "2023.2_Licitaiba",
          "2024-1-EducaMinas-backend",
          "2024-1-EducaMinas-frontend",
          "2024-1-Gastos-DF-Doc-Squad12",
          "2024-1-MinasDeCultura",
          "2024-1-Squad-10",
          "2024-1-Squad08",
          "2024-1-forUnB",
          "2024-1-squad04",
          "2024-2-AcheiUnB",
          "2024-2-Agio",
          "2024-2-ChamaControl",
          "2024-2-Datazonia",
          "2024-2-Lumina",
          "2024-2-Squad01",
          "2024-2-Squad06",
          "2024-2-SuaFinanca",
          "2024-2-Urbanize",
          "2025-1-Eletta",
          "2025-1-GovInsights",
          "2025-1-NoFluxoUNB",
          "2025-1-RelatAI",
          "2025-2-Eh_Fake",
          "2025-2-GuiaDev",
          "2025-2-InfoSchool",
          "2025-2-Integralizei_UnB",
          "2025-2-Lumina",
          "2025-2-Mural-UnB",
          "2025-2-OncoMap",
          "2025-2-Portal-dos-Professores",
          "2025-2-SeLiga",
          "2025-2-Squad-01",
          "2025-2-Squad12",
          "2025-2-Synapse",
          "2025.1-RelatoriosInteligentesBCB",
          "2025_1-Jakebot",
          "Avalia",
          "DFemObras",
          "DFemObras-2025.1",
          "Gastos-DF-Squad12",
          "LicitaBSB-24.1",
          "MDS-MonitoraBSB",
          "Mds-ArenaPesadelo",
          "ParticipeMais",
          "Projeto-P.I.T.E.R",
          "Qualifying-Software-Engineers-Undergraduates-in-DevOps",
          "Sonorus-2025.1",
          "Squad09-UnBHUB",
          "VIDAProject",
          "exemplogitpage",
          "mapadaacessibilidade",
          "portfolio-MDS",
          "squad03-r2",
          "teste"
        ]
      },
      {
        "name": "ananunesv",
        "commits": 0,
        "issues_created": 0,
        "issues_closed": 0,
        "prs_created": 1,
        "prs_closed": 0,
        "comments": 0,
        "repositories": [
          "Avalia",
          "Projeto-P.I.T.E.R"
        ]
      },
      {
        "name": "pedruck",
        "commits": 0,
        "issues_created": 0,
        "issues_closed": 0,
        "prs_created": 1,
        "prs_closed": 0,
        "comments": 0,
        "repositories": [
          "2025-2-Squad-01",
          "Avalia"
        ]
      },
      {
        "name": "guxvr",
        "commits": 0,
        "issues_created": 0,
        "issues_closed": 0,
        "prs_created": 1,
        "prs_closed": 0,
        "comments": 0,
        "repositories": [
          "2025-2-Squad-01",
          "Avalia"
        ]
      },
      {
        "name": "gpaulovit",
        "commits": 0,
        "issues_created": 0,
        "issues_closed": 0,
        "prs_created": 1,
        "prs_closed": 0,
        "comments": 0,
        "repositories": [
          "2025-2-Integralizei_UnB",
          "Avalia"
        ]
      },
      {
        "name": "HugoFreitass",
        "commits": 0,
        "issues_created": 0,
        "issues_closed": 0,
        "prs_created": 1,
        "prs_closed": 0,
        "comments": 0,
        "repositories": [
          "2025-2-GuiaDev",
          "Avalia"
        ]
      },
      {
        "name": "Fofodoido",
        "commits": 0,
        "issues_created": 0,
        "issues_closed": 0,
        "prs_created": 1,
        "prs_closed": 0,
        "comments": 0,
        "repositories": [
          "Avalia",
          "Projeto-P.I.T.E.R"
        ]
      },
      {
        "name": "MarcusVRezende",
        "commits": 0,
        "issues_created": 0,
        "issues_closed": 0,
        "prs_created": 1,
        "prs_closed": 0,
        "comments": 0,
        "repositories": [
          "2025-2-SeLiga",
          "Avalia"
        ]
      },
      {
        "name": "Romm-0",
        "commits": 0,
        "issues_created": 0,
        "issues_closed": 0,
        "prs_created": 1,
        "prs_closed": 0,
        "comments": 0,
        "repositories": [
          "2025-2-Eh_Fake",
          "Avalia"
        ]
      },
      {
        "name": "menali17",
        "commits": 0,
        "issues_created": 0,
        "issues_closed": 0,
        "prs_created": 1,
        "prs_closed": 0,
        "comments": 0,
        "repositories": [
          "2025-2-Integralizei_UnB",
          "Avalia"
        ]
      },
      {
        "name": "Flyxs",
        "commits": 0,
        "issues_created": 0,
        "issues_closed": 0,
        "prs_created": 1,
        "prs_closed": 0,
        "comments": 0,
        "repositories": [
          "2025-2-OncoMap",
          "Avalia"
        ]
      },
      {
        "name": "Jp-te",
        "commits": 0,
        "issues_created": 0,
        "issues_closed": 0,
        "prs_created": 1,
        "prs_closed": 0,
        "comments": 0,
        "repositories": [
          "2025-2-Squad12",
          "Avalia"
        ]
      },
      {
        "name": "Pirata2040",
        "commits": 0,
        "issues_created": 5,
        "issues_closed": 0,
        "prs_created": 0,
        "prs_closed": 0,
        "comments": 0,
        "repositories": [
          "Projeto-P.I.T.E.R"
        ]
      },
      {
        "name": "arthursouto09",
        "commits": 5,
        "issues_created": 0,
        "issues_closed": 0,
        "prs_created": 0,
        "prs_closed": 0,
        "comments": 0,
        "repositories": [
          "2025-2-Squad12"
        ]
      },
      {
        "name": "Ana",
        "commits": 2,
        "issues_created": 0,
        "issues_closed": 0,
        "prs_created": 0,
        "prs_closed": 0,
        "comments": 0,
        "repositories": [
          "2025-2-Integralizei_UnB"
        ]
      },
      {
        "name": "Paulo Vitor Gomes",
        "commits": 1,
        "issues_created": 0,
        "issues_closed": 0,
        "prs_created": 0,
        "prs_closed": 0,
        "comments": 0,
        "repositories": [
          "2025-2-Integralizei_UnB"
        ]
      }
    ]
  },
  {
    "date": "2025-11-15",
    "total_events": 28,
    "issues_created": 0,
    "issues_closed": 0,
    "prs_created": 0,
    "prs_closed": 0,
    "commits": 28,
    "comments": 0,
    "unique_users": 7,
    "unique_repos": 4,
    "authors": [
      {
        "name": "Github Actions",
        "commits": 1,
        "issues_created": 0,
        "issues_closed": 0,
        "prs_created": 0,
        "prs_closed": 0,
        "comments": 0,
        "repositories": [
          "2023-2-Squad04",
          "DFemObras",
          "DFemObras-2025.1",
          "LicitaBSB-24.1"
        ]
      },
      {
        "name": "Tiago",
        "commits": 4,
        "issues_created": 0,
        "issues_closed": 0,
        "prs_created": 0,
        "prs_closed": 0,
        "comments": 0,
        "repositories": [
          "2025-2-Lumina",
          "2025-2-Mural-UnB"
        ]
      },
      {
        "name": "apptrx",
        "commits": 16,
        "issues_created": 0,
        "issues_closed": 0,
        "prs_created": 0,
        "prs_closed": 0,
        "comments": 0,
        "repositories": [
          "2025-2-Mural-UnB"
        ]
      },
      {
        "name": "Carla Rocha",
        "commits": 1,
        "issues_created": 0,
        "issues_closed": 0,
        "prs_created": 0,
        "prs_closed": 0,
        "comments": 0,
        "repositories": [
          ".github",
          "2023-2-JuizVirtual",
          "2023-2-Squad01",
          "2023-2-Squad02-Desmatazonia",
          "2023-2-Squad03-LicitAL",
          "2023-2-Squad04",
          "2023-2-Squad05-TesouroMineiro",
          "2023-2-Squad07",
          "2023-2-Squad09-Gotinha",
          "2023-2-Squad10",
          "2023-2-SuaGradeUnB",
          "2023.2_DeOlhoRS",
          "2023.2_Gotinha",
          "2023.2_Licitaiba",
          "2024-1-EducaMinas-backend",
          "2024-1-EducaMinas-frontend",
          "2024-1-Gastos-DF-Doc-Squad12",
          "2024-1-MinasDeCultura",
          "2024-1-Squad-10",
          "2024-1-Squad08",
          "2024-1-forUnB",
          "2024-1-squad04",
          "2024-2-AcheiUnB",
          "2024-2-Agio",
          "2024-2-ChamaControl",
          "2024-2-Datazonia",
          "2024-2-Lumina",
          "2024-2-Squad01",
          "2024-2-Squad06",
          "2024-2-SuaFinanca",
          "2024-2-Urbanize",
          "2025-1-Eletta",
          "2025-1-GovInsights",
          "2025-1-NoFluxoUNB",
          "2025-1-RelatAI",
          "2025-2-Eh_Fake",
          "2025-2-GuiaDev",
          "2025-2-InfoSchool",
          "2025-2-Integralizei_UnB",
          "2025-2-Lumina",
          "2025-2-Mural-UnB",
          "2025-2-OncoMap",
          "2025-2-Portal-dos-Professores",
          "2025-2-SeLiga",
          "2025-2-Squad-01",
          "2025-2-Squad12",
          "2025-2-Synapse",
          "2025.1-RelatoriosInteligentesBCB",
          "2025_1-Jakebot",
          "Avalia",
          "DFemObras",
          "DFemObras-2025.1",
          "Gastos-DF-Squad12",
          "LicitaBSB-24.1",
          "MDS-MonitoraBSB",
          "Mds-ArenaPesadelo",
          "ParticipeMais",
          "Projeto-P.I.T.E.R",
          "Qualifying-Software-Engineers-Undergraduates-in-DevOps",
          "Sonorus-2025.1",
          "Squad09-UnBHUB",
          "VIDAProject",
          "exemplogitpage",
          "mapadaacessibilidade",
          "portfolio-MDS",
          "squad03-r2",
          "teste"
        ]
      },
      {
        "name": "Matheus Saraiva Camargo",
        "commits": 3,
        "issues_created": 0,
        "issues_closed": 0,
        "prs_created": 0,
        "prs_closed": 0,
        "comments": 0,
        "repositories": [
          "2025-2-Mural-UnB"
        ]
      },
      {
        "name": "LucasFT",
        "commits": 2,
        "issues_created": 0,
        "issues_closed": 0,
        "prs_created": 0,
        "prs_closed": 0,
        "comments": 0,
        "repositories": [
          "2025-2-Mural-UnB"
        ]
      },
      {
        "name": "TiagoUNB",
        "commits": 1,
        "issues_created": 0,
        "issues_closed": 0,
        "prs_created": 0,
        "prs_closed": 0,
        "comments": 0,
        "repositories": [
          "2025-2-Lumina"
        ]
      }
    ]
  },
  {
    "date": "2025-11-16",
    "total_events": 22,
    "issues_created": 0,
    "issues_closed": 0,
    "prs_created": 0,
    "prs_closed": 0,
    "commits": 22,
    "comments": 0,
    "unique_users": 8,
    "unique_repos": 4,
    "authors": [
      {
        "name": "Lucasft16",
        "commits": 2,
        "issues_created": 0,
        "issues_closed": 0,
        "prs_created": 0,
        "prs_closed": 0,
        "comments": 0,
        "repositories": [
          "2025-2-Mural-UnB"
        ]
      },
      {
        "name": "apptrx",
        "commits": 13,
        "issues_created": 0,
        "issues_closed": 0,
        "prs_created": 0,
        "prs_closed": 0,
        "comments": 0,
        "repositories": [
          "2025-2-Mural-UnB"
        ]
      },
      {
        "name": "Lucas Fujimoto Tokunaga",
        "commits": 1,
        "issues_created": 0,
        "issues_closed": 0,
        "prs_created": 0,
        "prs_closed": 0,
        "comments": 0,
        "repositories": [
          "2025-2-Mural-UnB"
        ]
      },
      {
        "name": "Rafael Oliveira Montagner Melatti",
        "commits": 1,
        "issues_created": 0,
        "issues_closed": 0,
        "prs_created": 0,
        "prs_closed": 0,
        "comments": 0,
        "repositories": [
          "2025-2-Eh_Fake"
        ]
      },
      {
        "name": "Gotc2607",
        "commits": 2,
        "issues_created": 0,
        "issues_closed": 0,
        "prs_created": 0,
        "prs_closed": 0,
        "comments": 0,
        "repositories": [
          "2025-2-OncoMap"
        ]
      },
      {
        "name": "Matheus Saraiva Camargo",
        "commits": 1,
        "issues_created": 0,
        "issues_closed": 0,
        "prs_created": 0,
        "prs_closed": 0,
        "comments": 0,
        "repositories": [
          "2025-2-Mural-UnB"
        ]
      },
      {
        "name": "Felype Gomes Ribeiro Carrijo",
        "commits": 1,
        "issues_created": 0,
        "issues_closed": 0,
        "prs_created": 0,
        "prs_closed": 0,
        "comments": 0,
        "repositories": [
          "2025-2-OncoMap"
        ]
      },
      {
        "name": "JoaoPedro",
        "commits": 1,
        "issues_created": 0,
        "issues_closed": 0,
        "prs_created": 0,
        "prs_closed": 0,
        "comments": 0,
        "repositories": [
          "2025-2-Lumina"
        ]
      }
    ]
  },
  {
    "date": "2025-11-17",
    "total_events": 2,
    "issues_created": 0,
    "issues_closed": 0,
    "prs_created": 0,
    "prs_closed": 0,
    "commits": 2,
    "comments": 0,
    "unique_users": 2,
    "unique_repos": 2,
    "authors": [
      {
        "name": "nathanpromao",
        "commits": 1,
        "issues_created": 0,
        "issues_closed": 0,
        "prs_created": 0,
        "prs_closed": 0,
        "comments": 0,
        "repositories": [
          "2025-2-Lumina"
        ]
      },
      {
        "name": "GitHub Actions Bot",
        "commits": 1,
        "issues_created": 0,
        "issues_closed": 0,
        "prs_created": 0,
        "prs_closed": 0,
        "comments": 0,
        "repositories": [
          "2025-2-Mural-UnB",
          "DFemObras",
          "DFemObras-2025.1"
        ]
      }
    ]
  }
]